#def get_flag():

  2           0 LOAD_CONST               1 ('J')
              3 STORE_FAST               0 (flag)

  3           6 LOAD_FAST                0 (flag)
              9 LOAD_CONST               2 ('H')
             12 INPLACE_ADD         
             13 STORE_FAST               0 (flag)

  4          16 LOAD_FAST                0 (flag)
             19 LOAD_CONST               3 ('t')
             22 INPLACE_ADD         
             23 STORE_FAST               0 (flag)

  5          26 LOAD_FAST                0 (flag)
             29 LOAD_CONST               4 ('C')
             32 INPLACE_ADD         
             33 STORE_FAST               0 (flag)

  6          36 LOAD_FAST                0 (flag)
             39 LOAD_CONST               5 ('4')
             42 INPLACE_ADD         
             43 STORE_FAST               0 (flag)

  7          46 LOAD_FAST                0 (flag)
             49 LOAD_CONST               6 ('B')
             52 INPLACE_ADD         
             53 STORE_FAST               0 (flag)

  8          56 LOAD_FAST                0 (flag)
             59 LOAD_CONST               7 ('S')
             62 INPLACE_ADD         
             63 STORE_FAST               0 (flag)

  9          66 LOAD_FAST                0 (flag)
             69 LOAD_CONST               8 ('K')
             72 INPLACE_ADD         
             73 STORE_FAST               0 (flag)

 10          76 LOAD_FAST                0 (flag)
             79 LOAD_CONST               9 ('{')
             82 INPLACE_ADD         
             83 STORE_FAST               0 (flag)

 12          86 LOAD_CONST              10 (0)
             89 STORE_FAST               1 (a)

 13          92 LOAD_CONST              10 (0)
             95 STORE_FAST               2 (b)

 14          98 LOAD_CONST              10 (0)
            101 STORE_FAST               3 (c)

 15         104 LOAD_CONST              10 (0)
            107 STORE_FAST               4 (d)

 16         110 LOAD_CONST              10 (0)
            113 STORE_FAST               5 (e)

 17         116 LOAD_CONST              10 (0)
            119 STORE_FAST               6 (f)

 18         122 LOAD_CONST              10 (0)
            125 STORE_FAST               7 (g)

 19         128 LOAD_CONST              10 (0)
            131 STORE_FAST               8 (h)

 20         134 LOAD_CONST              10 (0)
            137 STORE_FAST               9 (i)

 21         140 LOAD_CONST              10 (0)
            143 STORE_FAST              10 (j)

 22         146 LOAD_CONST              10 (0)
            149 STORE_FAST              11 (k)

 23         152 LOAD_CONST              10 (0)
            155 STORE_FAST              12 (l)

 24         158 LOAD_CONST              10 (0)
            161 STORE_FAST              13 (m)

 25         164 LOAD_CONST              10 (0)
            167 STORE_FAST              14 (n)

 26         170 LOAD_CONST              10 (0)
            173 STORE_FAST              15 (o)

 27         176 LOAD_CONST              10 (0)
            179 STORE_FAST              16 (p)

 28         182 LOAD_CONST              10 (0)
            185 STORE_FAST              17 (q)

 29         188 LOAD_CONST              10 (0)
            191 STORE_FAST              18 (r)

 30         194 LOAD_CONST              10 (0)
            197 STORE_FAST              19 (s)

 31         200 LOAD_CONST              10 (0)
            203 STORE_FAST              20 (t)

 32         206 LOAD_CONST              10 (0)
            209 STORE_FAST              21 (u)

 33         212 LOAD_FAST               12 (l)
            215 LOAD_CONST              11 (39)
            218 COMPARE_OP               4 (>)
            221 POP_JUMP_IF_FALSE      237

 34         224 LOAD_FAST                4 (d)
            227 LOAD_CONST              12 (6)
            230 INPLACE_SUBTRACT    
            231 STORE_FAST               4 (d)
            234 JUMP_FORWARD            10 (to 247)

 36     >>  237 LOAD_FAST                4 (d)
            240 LOAD_CONST              13 (10)
            243 INPLACE_ADD         
            244 STORE_FAST               4 (d)

 37     >>  247 LOAD_FAST                1 (a)
            250 LOAD_CONST              14 (25)
            253 COMPARE_OP               4 (>)
            256 POP_JUMP_IF_FALSE      272

 38         259 LOAD_FAST               19 (s)
            262 LOAD_CONST              15 (8)
            265 INPLACE_ADD         
            266 STORE_FAST              19 (s)
            269 JUMP_FORWARD            10 (to 282)

 40     >>  272 LOAD_FAST               19 (s)
            275 LOAD_CONST              16 (2)
            278 INPLACE_SUBTRACT    
            279 STORE_FAST              19 (s)

 41     >>  282 LOAD_FAST               13 (m)
            285 LOAD_CONST              17 (24)
            288 COMPARE_OP               0 (<)
            291 POP_JUMP_IF_FALSE      307

 42         294 LOAD_FAST               19 (s)
            297 LOAD_CONST              18 (1)
            300 INPLACE_SUBTRACT    
            301 STORE_FAST              19 (s)
            304 JUMP_FORWARD            10 (to 317)

 44     >>  307 LOAD_FAST               19 (s)
            310 LOAD_CONST              19 (3)
            313 INPLACE_SUBTRACT    
            314 STORE_FAST              19 (s)

 45     >>  317 LOAD_FAST               15 (o)
            320 LOAD_CONST              20 (17)
            323 COMPARE_OP               0 (<)
            326 POP_JUMP_IF_FALSE      342

 46         329 LOAD_FAST               20 (t)
            332 LOAD_CONST              21 (7)
            335 INPLACE_SUBTRACT    
            336 STORE_FAST              20 (t)
            339 JUMP_FORWARD            10 (to 352)

 48     >>  342 LOAD_FAST               20 (t)
            345 LOAD_CONST              22 (46)
            348 INPLACE_SUBTRACT    
            349 STORE_FAST              20 (t)

 49     >>  352 LOAD_FAST                1 (a)
            355 LOAD_CONST              14 (25)
            358 COMPARE_OP               4 (>)
            361 POP_JUMP_IF_FALSE      377

 50         364 LOAD_FAST                1 (a)
            367 LOAD_CONST              23 (21)
            370 INPLACE_SUBTRACT    
            371 STORE_FAST               1 (a)
            374 JUMP_FORWARD            10 (to 387)

 52     >>  377 LOAD_FAST                1 (a)
            380 LOAD_CONST              24 (31)
            383 INPLACE_SUBTRACT    
            384 STORE_FAST               1 (a)

 53     >>  387 LOAD_FAST               13 (m)
            390 LOAD_CONST              22 (46)
            393 COMPARE_OP               4 (>)
            396 POP_JUMP_IF_FALSE      412

 54         399 LOAD_FAST                1 (a)
            402 LOAD_CONST              23 (21)
            405 INPLACE_SUBTRACT    
            406 STORE_FAST               1 (a)
            409 JUMP_FORWARD            10 (to 422)

 56     >>  412 LOAD_FAST                1 (a)
            415 LOAD_CONST              23 (21)
            418 INPLACE_ADD         
            419 STORE_FAST               1 (a)

 57     >>  422 LOAD_FAST               18 (r)
            425 LOAD_CONST              25 (34)
            428 COMPARE_OP               0 (<)
            431 POP_JUMP_IF_FALSE      447

 58         434 LOAD_FAST                3 (c)
            437 LOAD_CONST              18 (1)
            440 INPLACE_ADD         
            441 STORE_FAST               3 (c)
            444 JUMP_FORWARD            10 (to 457)

 60     >>  447 LOAD_FAST                3 (c)
            450 LOAD_CONST              26 (50)
            453 INPLACE_SUBTRACT    
            454 STORE_FAST               3 (c)

 61     >>  457 LOAD_FAST               10 (j)
            460 LOAD_CONST              11 (39)
            463 COMPARE_OP               4 (>)
            466 POP_JUMP_IF_FALSE      482

 62         469 LOAD_FAST               19 (s)
            472 LOAD_CONST              27 (4)
            475 INPLACE_ADD         
            476 STORE_FAST              19 (s)
            479 JUMP_FORWARD            10 (to 492)

 64     >>  482 LOAD_FAST               19 (s)
            485 LOAD_CONST              18 (1)
            488 INPLACE_SUBTRACT    
            489 STORE_FAST              19 (s)

 65     >>  492 LOAD_FAST                9 (i)
            495 LOAD_CONST              16 (2)
            498 COMPARE_OP               0 (<)
            501 POP_JUMP_IF_FALSE      517

 66         504 LOAD_FAST               16 (p)
            507 LOAD_CONST              28 (91)
            510 INPLACE_SUBTRACT    
            511 STORE_FAST              16 (p)
            514 JUMP_FORWARD            10 (to 527)

 68     >>  517 LOAD_FAST               16 (p)
            520 LOAD_CONST              29 (15)
            523 INPLACE_ADD         
            524 STORE_FAST              16 (p)

 69     >>  527 LOAD_FAST                3 (c)
            530 LOAD_CONST              24 (31)
            533 COMPARE_OP               4 (>)
            536 POP_JUMP_IF_FALSE      552

 70         539 LOAD_FAST               19 (s)
            542 LOAD_CONST              14 (25)
            545 INPLACE_ADD         
            546 STORE_FAST              19 (s)
            549 JUMP_FORWARD            10 (to 562)

 72     >>  552 LOAD_FAST               19 (s)
            555 LOAD_CONST              10 (0)
            558 INPLACE_ADD         
            559 STORE_FAST              19 (s)

 73     >>  562 LOAD_FAST                9 (i)
            565 LOAD_CONST              18 (1)
            568 COMPARE_OP               0 (<)
            571 POP_JUMP_IF_FALSE      587

 74         574 LOAD_FAST               18 (r)
            577 LOAD_CONST              30 (19)
            580 INPLACE_ADD         
            581 STORE_FAST              18 (r)
            584 JUMP_FORWARD            10 (to 597)

 76     >>  587 LOAD_FAST               18 (r)
            590 LOAD_CONST              29 (15)
            593 INPLACE_SUBTRACT    
            594 STORE_FAST              18 (r)

 77     >>  597 LOAD_FAST                5 (e)
            600 LOAD_CONST              31 (9)
            603 COMPARE_OP               4 (>)
            606 POP_JUMP_IF_FALSE      622

 78         609 LOAD_FAST               20 (t)
            612 LOAD_CONST              32 (45)
            615 INPLACE_ADD         
            616 STORE_FAST              20 (t)
            619 JUMP_FORWARD            10 (to 632)

 80     >>  622 LOAD_FAST               20 (t)
            625 LOAD_CONST              31 (9)
            628 INPLACE_SUBTRACT    
            629 STORE_FAST              20 (t)

 81     >>  632 LOAD_FAST               13 (m)
            635 LOAD_CONST              15 (8)
            638 COMPARE_OP               0 (<)
            641 POP_JUMP_IF_FALSE      657

 82         644 LOAD_FAST                7 (g)
            647 LOAD_CONST              13 (10)
            650 INPLACE_SUBTRACT    
            651 STORE_FAST               7 (g)
            654 JUMP_FORWARD            10 (to 667)

 84     >>  657 LOAD_FAST                7 (g)
            660 LOAD_CONST              25 (34)
            663 INPLACE_ADD         
            664 STORE_FAST               7 (g)

 85     >>  667 LOAD_FAST               10 (j)
            670 LOAD_CONST              27 (4)
            673 COMPARE_OP               0 (<)
            676 POP_JUMP_IF_FALSE      692

 86         679 LOAD_FAST                2 (b)
            682 LOAD_CONST              18 (1)
            685 INPLACE_ADD         
            686 STORE_FAST               2 (b)
            689 JUMP_FORWARD            10 (to 702)

 88     >>  692 LOAD_FAST                2 (b)
            695 LOAD_CONST              23 (21)
            698 INPLACE_SUBTRACT    
            699 STORE_FAST               2 (b)

 89     >>  702 LOAD_FAST               11 (k)
            705 LOAD_CONST              33 (28)
            708 COMPARE_OP               0 (<)
            711 POP_JUMP_IF_FALSE      727

 90         714 LOAD_FAST               15 (o)
            717 LOAD_CONST              34 (14)
            720 INPLACE_SUBTRACT    
            721 STORE_FAST              15 (o)
            724 JUMP_FORWARD            10 (to 737)

 92     >>  727 LOAD_FAST               15 (o)
            730 LOAD_CONST              31 (9)
            733 INPLACE_SUBTRACT    
            734 STORE_FAST              15 (o)

 93     >>  737 LOAD_FAST               11 (k)
            740 LOAD_CONST              21 (7)
            743 COMPARE_OP               0 (<)
            746 POP_JUMP_IF_FALSE      762

 94         749 LOAD_FAST               16 (p)
            752 LOAD_CONST              35 (5)
            755 INPLACE_SUBTRACT    
            756 STORE_FAST              16 (p)
            759 JUMP_FORWARD            10 (to 772)

 96     >>  762 LOAD_FAST               16 (p)
            765 LOAD_CONST              36 (29)
            768 INPLACE_ADD         
            769 STORE_FAST              16 (p)

 97     >>  772 LOAD_FAST                2 (b)
            775 LOAD_CONST              37 (37)
            778 COMPARE_OP               4 (>)
            781 POP_JUMP_IF_FALSE      797

 98         784 LOAD_FAST               18 (r)
            787 LOAD_CONST              25 (34)
            790 INPLACE_SUBTRACT    
            791 STORE_FAST              18 (r)
            794 JUMP_FORWARD            10 (to 807)

100     >>  797 LOAD_FAST               18 (r)
            800 LOAD_CONST              38 (58)
            803 INPLACE_ADD         
            804 STORE_FAST              18 (r)

101     >>  807 LOAD_FAST                1 (a)
            810 LOAD_CONST              19 (3)
            813 COMPARE_OP               4 (>)
            816 POP_JUMP_IF_FALSE      832

102         819 LOAD_FAST               16 (p)
            822 LOAD_CONST              19 (3)
            825 INPLACE_SUBTRACT    
            826 STORE_FAST              16 (p)
            829 JUMP_FORWARD            10 (to 842)

104     >>  832 LOAD_FAST               16 (p)
            835 LOAD_CONST              23 (21)
            838 INPLACE_SUBTRACT    
            839 STORE_FAST              16 (p)

105     >>  842 LOAD_FAST               18 (r)
            845 LOAD_CONST              19 (3)
            848 COMPARE_OP               0 (<)
            851 POP_JUMP_IF_FALSE      867

106         854 LOAD_FAST               17 (q)
            857 LOAD_CONST              39 (41)
            860 INPLACE_ADD         
            861 STORE_FAST              17 (q)
            864 JUMP_FORWARD            10 (to 877)

108     >>  867 LOAD_FAST               17 (q)
            870 LOAD_CONST              27 (4)
            873 INPLACE_ADD         
            874 STORE_FAST              17 (q)

109     >>  877 LOAD_FAST                9 (i)
            880 LOAD_CONST              22 (46)
            883 COMPARE_OP               0 (<)
            886 POP_JUMP_IF_FALSE      902

110         889 LOAD_FAST                2 (b)
            892 LOAD_CONST              40 (30)
            895 INPLACE_SUBTRACT    
            896 STORE_FAST               2 (b)
            899 JUMP_FORWARD            10 (to 912)

112     >>  902 LOAD_FAST                2 (b)
            905 LOAD_CONST              41 (32)
            908 INPLACE_ADD         
            909 STORE_FAST               2 (b)

113     >>  912 LOAD_FAST                7 (g)
            915 LOAD_CONST              12 (6)
            918 COMPARE_OP               4 (>)
            921 POP_JUMP_IF_FALSE      937

114         924 LOAD_FAST                8 (h)
            927 LOAD_CONST              42 (48)
            930 INPLACE_SUBTRACT    
            931 STORE_FAST               8 (h)
            934 JUMP_FORWARD            10 (to 947)

116     >>  937 LOAD_FAST                8 (h)
            940 LOAD_CONST              43 (38)
            943 INPLACE_SUBTRACT    
            944 STORE_FAST               8 (h)

117     >>  947 LOAD_FAST                4 (d)
            950 LOAD_CONST              33 (28)
            953 COMPARE_OP               4 (>)
            956 POP_JUMP_IF_FALSE      972

118         959 LOAD_FAST               18 (r)
            962 LOAD_CONST              44 (33)
            965 INPLACE_ADD         
            966 STORE_FAST              18 (r)
            969 JUMP_FORWARD            10 (to 982)

120     >>  972 LOAD_FAST               18 (r)
            975 LOAD_CONST              45 (42)
            978 INPLACE_SUBTRACT    
            979 STORE_FAST              18 (r)

121     >>  982 LOAD_FAST                3 (c)
            985 LOAD_CONST              37 (37)
            988 COMPARE_OP               4 (>)
            991 POP_JUMP_IF_FALSE     1007

122         994 LOAD_FAST               20 (t)
            997 LOAD_CONST              46 (20)
           1000 INPLACE_ADD         
           1001 STORE_FAST              20 (t)
           1004 JUMP_FORWARD            10 (to 1017)

124     >> 1007 LOAD_FAST               20 (t)
           1010 LOAD_CONST              16 (2)
           1013 INPLACE_ADD         
           1014 STORE_FAST              20 (t)

125     >> 1017 LOAD_FAST               21 (u)
           1020 LOAD_CONST              47 (49)
           1023 COMPARE_OP               4 (>)
           1026 POP_JUMP_IF_FALSE     1042

126        1029 LOAD_FAST               13 (m)
           1032 LOAD_CONST              41 (32)
           1035 INPLACE_ADD         
           1036 STORE_FAST              13 (m)
           1039 JUMP_FORWARD            10 (to 1052)

128     >> 1042 LOAD_FAST               13 (m)
           1045 LOAD_CONST              43 (38)
           1048 INPLACE_ADD         
           1049 STORE_FAST              13 (m)

129     >> 1052 LOAD_FAST                6 (f)
           1055 LOAD_CONST              47 (49)
           1058 COMPARE_OP               0 (<)
           1061 POP_JUMP_IF_FALSE     1077

130        1064 LOAD_FAST               18 (r)
           1067 LOAD_CONST              48 (23)
           1070 INPLACE_SUBTRACT    
           1071 STORE_FAST              18 (r)
           1074 JUMP_FORWARD            10 (to 1087)

132     >> 1077 LOAD_FAST               18 (r)
           1080 LOAD_CONST              49 (11)
           1083 INPLACE_ADD         
           1084 STORE_FAST              18 (r)

133     >> 1087 LOAD_FAST                3 (c)
           1090 LOAD_CONST              15 (8)
           1093 COMPARE_OP               0 (<)
           1096 POP_JUMP_IF_FALSE     1112

134        1099 LOAD_FAST                4 (d)
           1102 LOAD_CONST              13 (10)
           1105 INPLACE_ADD         
           1106 STORE_FAST               4 (d)
           1109 JUMP_FORWARD            10 (to 1122)

136     >> 1112 LOAD_FAST                4 (d)
           1115 LOAD_CONST              21 (7)
           1118 INPLACE_ADD         
           1119 STORE_FAST               4 (d)

137     >> 1122 LOAD_FAST               12 (l)
           1125 LOAD_CONST              50 (22)
           1128 COMPARE_OP               0 (<)
           1131 POP_JUMP_IF_FALSE     1147

138        1134 LOAD_FAST               14 (n)
           1137 LOAD_CONST              18 (1)
           1140 INPLACE_SUBTRACT    
           1141 STORE_FAST              14 (n)
           1144 JUMP_FORWARD            10 (to 1157)

140     >> 1147 LOAD_FAST               14 (n)
           1150 LOAD_CONST              48 (23)
           1153 INPLACE_SUBTRACT    
           1154 STORE_FAST              14 (n)

141     >> 1157 LOAD_FAST               15 (o)
           1160 LOAD_CONST              44 (33)
           1163 COMPARE_OP               0 (<)
           1166 POP_JUMP_IF_FALSE     1182

142        1169 LOAD_FAST                5 (e)
           1172 LOAD_CONST              19 (3)
           1175 INPLACE_ADD         
           1176 STORE_FAST               5 (e)
           1179 JUMP_FORWARD            10 (to 1192)

144     >> 1182 LOAD_FAST                5 (e)
           1185 LOAD_CONST              51 (40)
           1188 INPLACE_ADD         
           1189 STORE_FAST               5 (e)

145     >> 1192 LOAD_FAST               13 (m)
           1195 LOAD_CONST              22 (46)
           1198 COMPARE_OP               4 (>)
           1201 POP_JUMP_IF_FALSE     1217

146        1204 LOAD_FAST               14 (n)
           1207 LOAD_CONST              24 (31)
           1210 INPLACE_ADD         
           1211 STORE_FAST              14 (n)
           1214 JUMP_FORWARD            10 (to 1227)

148     >> 1217 LOAD_FAST               14 (n)
           1220 LOAD_CONST              18 (1)
           1223 INPLACE_SUBTRACT    
           1224 STORE_FAST              14 (n)

149     >> 1227 LOAD_FAST               14 (n)
           1230 LOAD_CONST              19 (3)
           1233 COMPARE_OP               4 (>)
           1236 POP_JUMP_IF_FALSE     1252

150        1239 LOAD_FAST                2 (b)
           1242 LOAD_CONST              19 (3)
           1245 INPLACE_SUBTRACT    
           1246 STORE_FAST               2 (b)
           1249 JUMP_FORWARD            10 (to 1262)

152     >> 1252 LOAD_FAST                2 (b)
           1255 LOAD_CONST              27 (4)
           1258 INPLACE_SUBTRACT    
           1259 STORE_FAST               2 (b)

153     >> 1262 LOAD_FAST               12 (l)
           1265 LOAD_CONST              50 (22)
           1268 COMPARE_OP               4 (>)
           1271 POP_JUMP_IF_FALSE     1287

154        1274 LOAD_FAST                6 (f)
           1277 LOAD_CONST              52 (16)
           1280 INPLACE_SUBTRACT    
           1281 STORE_FAST               6 (f)
           1284 JUMP_FORWARD            10 (to 1297)

156     >> 1287 LOAD_FAST                6 (f)
           1290 LOAD_CONST              30 (19)
           1293 INPLACE_ADD         
           1294 STORE_FAST               6 (f)

157     >> 1297 LOAD_FAST                3 (c)
           1300 LOAD_CONST              46 (20)
           1303 COMPARE_OP               0 (<)
           1306 POP_JUMP_IF_FALSE     1322

158        1309 LOAD_FAST               11 (k)
           1312 LOAD_CONST              35 (5)
           1315 INPLACE_SUBTRACT    
           1316 STORE_FAST              11 (k)
           1319 JUMP_FORWARD            10 (to 1332)

160     >> 1322 LOAD_FAST               11 (k)
           1325 LOAD_CONST              18 (1)
           1328 INPLACE_ADD         
           1329 STORE_FAST              11 (k)

161     >> 1332 LOAD_FAST               17 (q)
           1335 LOAD_CONST              47 (49)
           1338 COMPARE_OP               4 (>)
           1341 POP_JUMP_IF_FALSE     1357

162        1344 LOAD_FAST               16 (p)
           1347 LOAD_CONST              43 (38)
           1350 INPLACE_ADD         
           1351 STORE_FAST              16 (p)
           1354 JUMP_FORWARD            10 (to 1367)

164     >> 1357 LOAD_FAST               16 (p)
           1360 LOAD_CONST              31 (9)
           1363 INPLACE_SUBTRACT    
           1364 STORE_FAST              16 (p)

165     >> 1367 LOAD_FAST               13 (m)
           1370 LOAD_CONST              18 (1)
           1373 COMPARE_OP               4 (>)
           1376 POP_JUMP_IF_FALSE     1392

166        1379 LOAD_FAST                9 (i)
           1382 LOAD_CONST              13 (10)
           1385 INPLACE_SUBTRACT    
           1386 STORE_FAST               9 (i)
           1389 JUMP_FORWARD            10 (to 1402)

168     >> 1392 LOAD_FAST                9 (i)
           1395 LOAD_CONST              27 (4)
           1398 INPLACE_SUBTRACT    
           1399 STORE_FAST               9 (i)

169     >> 1402 LOAD_FAST               12 (l)
           1405 LOAD_CONST              48 (23)
           1408 COMPARE_OP               0 (<)
           1411 POP_JUMP_IF_FALSE     1427

170        1414 LOAD_FAST                7 (g)
           1417 LOAD_CONST              12 (6)
           1420 INPLACE_ADD         
           1421 STORE_FAST               7 (g)
           1424 JUMP_FORWARD            10 (to 1437)

172     >> 1427 LOAD_FAST                7 (g)
           1430 LOAD_CONST              53 (12)
           1433 INPLACE_SUBTRACT    
           1434 STORE_FAST               7 (g)

173     >> 1437 LOAD_FAST                2 (b)
           1440 LOAD_CONST              46 (20)
           1443 COMPARE_OP               0 (<)
           1446 POP_JUMP_IF_FALSE     1462

174        1449 LOAD_FAST               20 (t)
           1452 LOAD_CONST              18 (1)
           1455 INPLACE_ADD         
           1456 STORE_FAST              20 (t)
           1459 JUMP_FORWARD            10 (to 1472)

176     >> 1462 LOAD_FAST               20 (t)
           1465 LOAD_CONST              27 (4)
           1468 INPLACE_SUBTRACT    
           1469 STORE_FAST              20 (t)

177     >> 1472 LOAD_FAST               12 (l)
           1475 LOAD_CONST              18 (1)
           1478 COMPARE_OP               0 (<)
           1481 POP_JUMP_IF_FALSE     1497

178        1484 LOAD_FAST                7 (g)
           1487 LOAD_CONST              16 (2)
           1490 INPLACE_ADD         
           1491 STORE_FAST               7 (g)
           1494 JUMP_FORWARD            10 (to 1507)

180     >> 1497 LOAD_FAST                7 (g)
           1500 LOAD_CONST              33 (28)
           1503 INPLACE_SUBTRACT    
           1504 STORE_FAST               7 (g)

181     >> 1507 LOAD_FAST                3 (c)
           1510 LOAD_CONST              34 (14)
           1513 COMPARE_OP               0 (<)
           1516 POP_JUMP_IF_FALSE     1532

182        1519 LOAD_FAST               10 (j)
           1522 LOAD_CONST              33 (28)
           1525 INPLACE_SUBTRACT    
           1526 STORE_FAST              10 (j)
           1529 JUMP_FORWARD            10 (to 1542)

184     >> 1532 LOAD_FAST               10 (j)
           1535 LOAD_CONST              20 (17)
           1538 INPLACE_SUBTRACT    
           1539 STORE_FAST              10 (j)

185     >> 1542 LOAD_FAST                8 (h)
           1545 LOAD_CONST              45 (42)
           1548 COMPARE_OP               4 (>)
           1551 POP_JUMP_IF_FALSE     1567

186        1554 LOAD_FAST               13 (m)
           1557 LOAD_CONST              12 (6)
           1560 INPLACE_ADD         
           1561 STORE_FAST              13 (m)
           1564 JUMP_FORWARD            10 (to 1577)

188     >> 1567 LOAD_FAST               13 (m)
           1570 LOAD_CONST              54 (61)
           1573 INPLACE_SUBTRACT    
           1574 STORE_FAST              13 (m)

189     >> 1577 LOAD_FAST               17 (q)
           1580 LOAD_CONST              55 (44)
           1583 COMPARE_OP               0 (<)
           1586 POP_JUMP_IF_FALSE     1602

190        1589 LOAD_FAST               14 (n)
           1592 LOAD_CONST              55 (44)
           1595 INPLACE_ADD         
           1596 STORE_FAST              14 (n)
           1599 JUMP_FORWARD            10 (to 1612)

192     >> 1602 LOAD_FAST               14 (n)
           1605 LOAD_CONST              40 (30)
           1608 INPLACE_SUBTRACT    
           1609 STORE_FAST              14 (n)

193     >> 1612 LOAD_FAST               19 (s)
           1615 LOAD_CONST              53 (12)
           1618 COMPARE_OP               0 (<)
           1621 POP_JUMP_IF_FALSE     1637

194        1624 LOAD_FAST                5 (e)
           1627 LOAD_CONST              10 (0)
           1630 INPLACE_ADD         
           1631 STORE_FAST               5 (e)
           1634 JUMP_FORWARD            10 (to 1647)

196     >> 1637 LOAD_FAST                5 (e)
           1640 LOAD_CONST              42 (48)
           1643 INPLACE_ADD         
           1644 STORE_FAST               5 (e)

197     >> 1647 LOAD_FAST                9 (i)
           1650 LOAD_CONST              56 (13)
           1653 COMPARE_OP               4 (>)
           1656 POP_JUMP_IF_FALSE     1672

198        1659 LOAD_FAST               13 (m)
           1662 LOAD_CONST              11 (39)
           1665 INPLACE_ADD         
           1666 STORE_FAST              13 (m)
           1669 JUMP_FORWARD            10 (to 1682)

200     >> 1672 LOAD_FAST               13 (m)
           1675 LOAD_CONST              25 (34)
           1678 INPLACE_SUBTRACT    
           1679 STORE_FAST              13 (m)

201     >> 1682 LOAD_FAST               12 (l)
           1685 LOAD_CONST              14 (25)
           1688 COMPARE_OP               4 (>)
           1691 POP_JUMP_IF_FALSE     1707

202        1694 LOAD_FAST               15 (o)
           1697 LOAD_CONST              39 (41)
           1700 INPLACE_ADD         
           1701 STORE_FAST              15 (o)
           1704 JUMP_FORWARD            10 (to 1717)

204     >> 1707 LOAD_FAST               15 (o)
           1710 LOAD_CONST              10 (0)
           1713 INPLACE_ADD         
           1714 STORE_FAST              15 (o)

205     >> 1717 LOAD_FAST                4 (d)
           1720 LOAD_CONST              36 (29)
           1723 COMPARE_OP               4 (>)
           1726 POP_JUMP_IF_FALSE     1742

206        1729 LOAD_FAST               18 (r)
           1732 LOAD_CONST              20 (17)
           1735 INPLACE_ADD         
           1736 STORE_FAST              18 (r)
           1739 JUMP_FORWARD            10 (to 1752)

208     >> 1742 LOAD_FAST               18 (r)
           1745 LOAD_CONST              10 (0)
           1748 INPLACE_ADD         
           1749 STORE_FAST              18 (r)

209     >> 1752 LOAD_FAST                3 (c)
           1755 LOAD_CONST              47 (49)
           1758 COMPARE_OP               4 (>)
           1761 POP_JUMP_IF_FALSE     1777

210        1764 LOAD_FAST               15 (o)
           1767 LOAD_CONST              46 (20)
           1770 INPLACE_SUBTRACT    
           1771 STORE_FAST              15 (o)
           1774 JUMP_FORWARD            10 (to 1787)

212     >> 1777 LOAD_FAST               15 (o)
           1780 LOAD_CONST              10 (0)
           1783 INPLACE_ADD         
           1784 STORE_FAST              15 (o)

213     >> 1787 LOAD_FAST               14 (n)
           1790 LOAD_CONST              16 (2)
           1793 COMPARE_OP               4 (>)
           1796 POP_JUMP_IF_FALSE     1812

214        1799 LOAD_FAST                9 (i)
           1802 LOAD_CONST              30 (19)
           1805 INPLACE_ADD         
           1806 STORE_FAST               9 (i)
           1809 JUMP_FORWARD            10 (to 1822)

216     >> 1812 LOAD_FAST                9 (i)
           1815 LOAD_CONST              47 (49)
           1818 INPLACE_SUBTRACT    
           1819 STORE_FAST               9 (i)

217     >> 1822 LOAD_FAST                9 (i)
           1825 LOAD_CONST              49 (11)
           1828 COMPARE_OP               4 (>)
           1831 POP_JUMP_IF_FALSE     1847

218        1834 LOAD_FAST               16 (p)
           1837 LOAD_CONST              47 (49)
           1840 INPLACE_ADD         
           1841 STORE_FAST              16 (p)
           1844 JUMP_FORWARD            10 (to 1857)

220     >> 1847 LOAD_FAST               16 (p)
           1850 LOAD_CONST              56 (13)
           1853 INPLACE_ADD         
           1854 STORE_FAST              16 (p)

221     >> 1857 LOAD_FAST               16 (p)
           1860 LOAD_CONST              24 (31)
           1863 COMPARE_OP               4 (>)
           1866 POP_JUMP_IF_FALSE     1882

222        1869 LOAD_FAST                5 (e)
           1872 LOAD_CONST              25 (34)
           1875 INPLACE_SUBTRACT    
           1876 STORE_FAST               5 (e)
           1879 JUMP_FORWARD            10 (to 1892)

224     >> 1882 LOAD_FAST                5 (e)
           1885 LOAD_CONST              57 (56)
           1888 INPLACE_ADD         
           1889 STORE_FAST               5 (e)

225     >> 1892 LOAD_FAST                7 (g)
           1895 LOAD_CONST              27 (4)
           1898 COMPARE_OP               0 (<)
           1901 POP_JUMP_IF_FALSE     1917

226        1904 LOAD_FAST               20 (t)
           1907 LOAD_CONST              58 (90)
           1910 INPLACE_ADD         
           1911 STORE_FAST              20 (t)
           1914 JUMP_FORWARD            10 (to 1927)

228     >> 1917 LOAD_FAST               20 (t)
           1920 LOAD_CONST              23 (21)
           1923 INPLACE_SUBTRACT    
           1924 STORE_FAST              20 (t)

229     >> 1927 LOAD_FAST               13 (m)
           1930 LOAD_CONST              30 (19)
           1933 COMPARE_OP               4 (>)
           1936 POP_JUMP_IF_FALSE     1952

230        1939 LOAD_FAST               10 (j)
           1942 LOAD_CONST              30 (19)
           1945 INPLACE_ADD         
           1946 STORE_FAST              10 (j)
           1949 JUMP_FORWARD            10 (to 1962)

232     >> 1952 LOAD_FAST               10 (j)
           1955 LOAD_CONST              59 (231)
           1958 INPLACE_ADD         
           1959 STORE_FAST              10 (j)

233     >> 1962 LOAD_FAST               15 (o)
           1965 LOAD_CONST              30 (19)
           1968 COMPARE_OP               0 (<)
           1971 POP_JUMP_IF_FALSE     1987

234        1974 LOAD_FAST               13 (m)
           1977 LOAD_CONST              60 (59)
           1980 INPLACE_ADD         
           1981 STORE_FAST              13 (m)
           1984 JUMP_FORWARD            10 (to 1997)

236     >> 1987 LOAD_FAST               13 (m)
           1990 LOAD_CONST              29 (15)
           1993 INPLACE_ADD         
           1994 STORE_FAST              13 (m)

237     >> 1997 LOAD_FAST                7 (g)
           2000 LOAD_CONST              34 (14)
           2003 COMPARE_OP               4 (>)
           2006 POP_JUMP_IF_FALSE     2022

238        2009 LOAD_FAST                5 (e)
           2012 LOAD_CONST              15 (8)
           2015 INPLACE_SUBTRACT    
           2016 STORE_FAST               5 (e)
           2019 JUMP_FORWARD            10 (to 2032)

240     >> 2022 LOAD_FAST                5 (e)
           2025 LOAD_CONST              12 (6)
           2028 INPLACE_SUBTRACT    
           2029 STORE_FAST               5 (e)

241     >> 2032 LOAD_FAST                8 (h)
           2035 LOAD_CONST              12 (6)
           2038 COMPARE_OP               4 (>)
           2041 POP_JUMP_IF_FALSE     2057

242        2044 LOAD_FAST               15 (o)
           2047 LOAD_CONST              25 (34)
           2050 INPLACE_SUBTRACT    
           2051 STORE_FAST              15 (o)
           2054 JUMP_FORWARD            10 (to 2067)

244     >> 2057 LOAD_FAST               15 (o)
           2060 LOAD_CONST              27 (4)
           2063 INPLACE_SUBTRACT    
           2064 STORE_FAST              15 (o)

245     >> 2067 LOAD_FAST                6 (f)
           2070 LOAD_CONST              14 (25)
           2073 COMPARE_OP               4 (>)
           2076 POP_JUMP_IF_FALSE     2092

246        2079 LOAD_FAST               20 (t)
           2082 LOAD_CONST              44 (33)
           2085 INPLACE_SUBTRACT    
           2086 STORE_FAST              20 (t)
           2089 JUMP_FORWARD            10 (to 2102)

248     >> 2092 LOAD_FAST               20 (t)
           2095 LOAD_CONST              16 (2)
           2098 INPLACE_ADD         
           2099 STORE_FAST              20 (t)

249     >> 2102 LOAD_FAST                1 (a)
           2105 LOAD_CONST              15 (8)
           2108 COMPARE_OP               4 (>)
           2111 POP_JUMP_IF_FALSE     2127

250        2114 LOAD_FAST               17 (q)
           2117 LOAD_CONST              30 (19)
           2120 INPLACE_ADD         
           2121 STORE_FAST              17 (q)
           2124 JUMP_FORWARD            10 (to 2137)

252     >> 2127 LOAD_FAST               17 (q)
           2130 LOAD_CONST              18 (1)
           2133 INPLACE_ADD         
           2134 STORE_FAST              17 (q)

253     >> 2137 LOAD_FAST               10 (j)
           2140 LOAD_CONST              12 (6)
           2143 COMPARE_OP               0 (<)
           2146 POP_JUMP_IF_FALSE     2162

254        2149 LOAD_FAST               17 (q)
           2152 LOAD_CONST              40 (30)
           2155 INPLACE_SUBTRACT    
           2156 STORE_FAST              17 (q)
           2159 JUMP_FORWARD            10 (to 2172)

256     >> 2162 LOAD_FAST               17 (q)
           2165 LOAD_CONST              44 (33)
           2168 INPLACE_ADD         
           2169 STORE_FAST              17 (q)

257     >> 2172 LOAD_FAST                2 (b)
           2175 LOAD_CONST              27 (4)
           2178 COMPARE_OP               4 (>)
           2181 POP_JUMP_IF_FALSE     2197

258        2184 LOAD_FAST               12 (l)
           2187 LOAD_CONST              26 (50)
           2190 INPLACE_SUBTRACT    
           2191 STORE_FAST              12 (l)
           2194 JUMP_FORWARD            10 (to 2207)

260     >> 2197 LOAD_FAST               12 (l)
           2200 LOAD_CONST              55 (44)
           2203 INPLACE_ADD         
           2204 STORE_FAST              12 (l)

261     >> 2207 LOAD_FAST                8 (h)
           2210 LOAD_CONST              13 (10)
           2213 COMPARE_OP               0 (<)
           2216 POP_JUMP_IF_FALSE     2232

262        2219 LOAD_FAST               10 (j)
           2222 LOAD_CONST              24 (31)
           2225 INPLACE_SUBTRACT    
           2226 STORE_FAST              10 (j)
           2229 JUMP_FORWARD            10 (to 2242)

264     >> 2232 LOAD_FAST               10 (j)
           2235 LOAD_CONST              22 (46)
           2238 INPLACE_SUBTRACT    
           2239 STORE_FAST              10 (j)

265     >> 2242 LOAD_FAST               17 (q)
           2245 LOAD_CONST              13 (10)
           2248 COMPARE_OP               4 (>)
           2251 POP_JUMP_IF_FALSE     2267

266        2254 LOAD_FAST               14 (n)
           2257 LOAD_CONST              18 (1)
           2260 INPLACE_SUBTRACT    
           2261 STORE_FAST              14 (n)
           2264 JUMP_FORWARD            10 (to 2277)

268     >> 2267 LOAD_FAST               14 (n)
           2270 LOAD_CONST              24 (31)
           2273 INPLACE_SUBTRACT    
           2274 STORE_FAST              14 (n)

269     >> 2277 LOAD_FAST                8 (h)
           2280 LOAD_CONST              10 (0)
           2283 COMPARE_OP               4 (>)
           2286 POP_JUMP_IF_FALSE     2302

270        2289 LOAD_FAST                7 (g)
           2292 LOAD_CONST              35 (5)
           2295 INPLACE_ADD         
           2296 STORE_FAST               7 (g)
           2299 JUMP_FORWARD            10 (to 2312)

272     >> 2302 LOAD_FAST                7 (g)
           2305 LOAD_CONST              16 (2)
           2308 INPLACE_ADD         
           2309 STORE_FAST               7 (g)

273     >> 2312 LOAD_FAST               18 (r)
           2315 LOAD_CONST              13 (10)
           2318 COMPARE_OP               0 (<)
           2321 POP_JUMP_IF_FALSE     2337

274        2324 LOAD_FAST               14 (n)
           2327 LOAD_CONST              61 (47)
           2330 INPLACE_SUBTRACT    
           2331 STORE_FAST              14 (n)
           2334 JUMP_FORWARD            10 (to 2347)

276     >> 2337 LOAD_FAST               14 (n)
           2340 LOAD_CONST              15 (8)
           2343 INPLACE_SUBTRACT    
           2344 STORE_FAST              14 (n)

277     >> 2347 LOAD_FAST               20 (t)
           2350 LOAD_CONST              61 (47)
           2353 COMPARE_OP               4 (>)
           2356 POP_JUMP_IF_FALSE     2372

278        2359 LOAD_FAST                6 (f)
           2362 LOAD_CONST              30 (19)
           2365 INPLACE_SUBTRACT    
           2366 STORE_FAST               6 (f)
           2369 JUMP_FORWARD            10 (to 2382)

280     >> 2372 LOAD_FAST                6 (f)
           2375 LOAD_CONST              26 (50)
           2378 INPLACE_ADD         
           2379 STORE_FAST               6 (f)

281     >> 2382 LOAD_FAST               10 (j)
           2385 LOAD_CONST              40 (30)
           2388 COMPARE_OP               4 (>)
           2391 POP_JUMP_IF_FALSE     2407

282        2394 LOAD_FAST                1 (a)
           2397 LOAD_CONST              62 (103)
           2400 INPLACE_ADD         
           2401 STORE_FAST               1 (a)
           2404 JUMP_FORWARD            10 (to 2417)

284     >> 2407 LOAD_FAST                1 (a)
           2410 LOAD_CONST              53 (12)
           2413 INPLACE_ADD         
           2414 STORE_FAST               1 (a)

285     >> 2417 LOAD_FAST                5 (e)
           2420 LOAD_CONST              53 (12)
           2423 COMPARE_OP               4 (>)
           2426 POP_JUMP_IF_FALSE     2442

286        2429 LOAD_FAST                5 (e)
           2432 LOAD_CONST              56 (13)
           2435 INPLACE_ADD         
           2436 STORE_FAST               5 (e)
           2439 JUMP_FORWARD            10 (to 2452)

288     >> 2442 LOAD_FAST                5 (e)
           2445 LOAD_CONST              63 (36)
           2448 INPLACE_ADD         
           2449 STORE_FAST               5 (e)

289     >> 2452 LOAD_FAST               12 (l)
           2455 LOAD_CONST              27 (4)
           2458 COMPARE_OP               4 (>)
           2461 POP_JUMP_IF_FALSE     2477

290        2464 LOAD_FAST               18 (r)
           2467 LOAD_CONST              64 (67)
           2470 INPLACE_ADD         
           2471 STORE_FAST              18 (r)
           2474 JUMP_FORWARD            10 (to 2487)

292     >> 2477 LOAD_FAST               18 (r)
           2480 LOAD_CONST              32 (45)
           2483 INPLACE_SUBTRACT    
           2484 STORE_FAST              18 (r)

293     >> 2487 LOAD_FAST               12 (l)
           2490 LOAD_CONST              52 (16)
           2493 COMPARE_OP               0 (<)
           2496 POP_JUMP_IF_FALSE     2512

294        2499 LOAD_FAST               19 (s)
           2502 LOAD_CONST              24 (31)
           2505 INPLACE_ADD         
           2506 STORE_FAST              19 (s)
           2509 JUMP_FORWARD            10 (to 2522)

296     >> 2512 LOAD_FAST               19 (s)
           2515 LOAD_CONST              60 (59)
           2518 INPLACE_ADD         
           2519 STORE_FAST              19 (s)

297     >> 2522 LOAD_FAST               10 (j)
           2525 LOAD_CONST              65 (35)
           2528 COMPARE_OP               4 (>)
           2531 POP_JUMP_IF_FALSE     2547

298        2534 LOAD_FAST               21 (u)
           2537 LOAD_CONST              46 (20)
           2540 INPLACE_ADD         
           2541 STORE_FAST              21 (u)
           2544 JUMP_FORWARD            10 (to 2557)

300     >> 2547 LOAD_FAST               21 (u)
           2550 LOAD_CONST              41 (32)
           2553 INPLACE_ADD         
           2554 STORE_FAST              21 (u)

301     >> 2557 LOAD_FAST                5 (e)
           2560 LOAD_CONST              19 (3)
           2563 COMPARE_OP               0 (<)
           2566 POP_JUMP_IF_FALSE     2582

302        2569 LOAD_FAST               11 (k)
           2572 LOAD_CONST              45 (42)
           2575 INPLACE_ADD         
           2576 STORE_FAST              11 (k)
           2579 JUMP_FORWARD            10 (to 2592)

304     >> 2582 LOAD_FAST               11 (k)
           2585 LOAD_CONST              66 (27)
           2588 INPLACE_SUBTRACT    
           2589 STORE_FAST              11 (k)

305     >> 2592 LOAD_FAST               11 (k)
           2595 LOAD_CONST              25 (34)
           2598 COMPARE_OP               0 (<)
           2601 POP_JUMP_IF_FALSE     2617

306        2604 LOAD_FAST                9 (i)
           2607 LOAD_CONST              23 (21)
           2610 INPLACE_SUBTRACT    
           2611 STORE_FAST               9 (i)
           2614 JUMP_FORWARD            10 (to 2627)

308     >> 2617 LOAD_FAST                9 (i)
           2620 LOAD_CONST              33 (28)
           2623 INPLACE_ADD         
           2624 STORE_FAST               9 (i)

309     >> 2627 LOAD_FAST               19 (s)
           2630 LOAD_CONST              30 (19)
           2633 COMPARE_OP               4 (>)
           2636 POP_JUMP_IF_FALSE     2652

310        2639 LOAD_FAST               19 (s)
           2642 LOAD_CONST              53 (12)
           2645 INPLACE_SUBTRACT    
           2646 STORE_FAST              19 (s)
           2649 JUMP_FORWARD            10 (to 2662)

312     >> 2652 LOAD_FAST               19 (s)
           2655 LOAD_CONST              49 (11)
           2658 INPLACE_ADD         
           2659 STORE_FAST              19 (s)

313     >> 2662 LOAD_FAST               19 (s)
           2665 LOAD_CONST              24 (31)
           2668 COMPARE_OP               0 (<)
           2671 POP_JUMP_IF_FALSE     2687

314        2674 LOAD_FAST                6 (f)
           2677 LOAD_CONST              67 (26)
           2680 INPLACE_ADD         
           2681 STORE_FAST               6 (f)
           2684 JUMP_FORWARD            10 (to 2697)

316     >> 2687 LOAD_FAST                6 (f)
           2690 LOAD_CONST              56 (13)
           2693 INPLACE_SUBTRACT    
           2694 STORE_FAST               6 (f)

317     >> 2697 LOAD_FAST                7 (g)
           2700 LOAD_CONST              52 (16)
           2703 COMPARE_OP               4 (>)
           2706 POP_JUMP_IF_FALSE     2722

318        2709 LOAD_FAST               11 (k)
           2712 LOAD_CONST              67 (26)
           2715 INPLACE_ADD         
           2716 STORE_FAST              11 (k)
           2719 JUMP_FORWARD            10 (to 2732)

320     >> 2722 LOAD_FAST               11 (k)
           2725 LOAD_CONST              48 (23)
           2728 INPLACE_SUBTRACT    
           2729 STORE_FAST              11 (k)

321     >> 2732 LOAD_FAST                9 (i)
           2735 LOAD_CONST              26 (50)
           2738 COMPARE_OP               4 (>)
           2741 POP_JUMP_IF_FALSE     2757

322        2744 LOAD_FAST                8 (h)
           2747 LOAD_CONST              25 (34)
           2750 INPLACE_SUBTRACT    
           2751 STORE_FAST               8 (h)
           2754 JUMP_FORWARD            10 (to 2767)

324     >> 2757 LOAD_FAST                8 (h)
           2760 LOAD_CONST              31 (9)
           2763 INPLACE_ADD         
           2764 STORE_FAST               8 (h)

325     >> 2767 LOAD_FAST                2 (b)
           2770 LOAD_CONST              42 (48)
           2773 COMPARE_OP               0 (<)
           2776 POP_JUMP_IF_FALSE     2792

326        2779 LOAD_FAST                4 (d)
           2782 LOAD_CONST              23 (21)
           2785 INPLACE_ADD         
           2786 STORE_FAST               4 (d)
           2789 JUMP_FORWARD            10 (to 2802)

328     >> 2792 LOAD_FAST                4 (d)
           2795 LOAD_CONST              42 (48)
           2798 INPLACE_SUBTRACT    
           2799 STORE_FAST               4 (d)

329     >> 2802 LOAD_FAST                3 (c)
           2805 LOAD_CONST              66 (27)
           2808 COMPARE_OP               0 (<)
           2811 POP_JUMP_IF_FALSE     2827

330        2814 LOAD_FAST                9 (i)
           2817 LOAD_CONST              68 (65)
           2820 INPLACE_ADD         
           2821 STORE_FAST               9 (i)
           2824 JUMP_FORWARD            10 (to 2837)

332     >> 2827 LOAD_FAST                9 (i)
           2830 LOAD_CONST              52 (16)
           2833 INPLACE_ADD         
           2834 STORE_FAST               9 (i)

333     >> 2837 LOAD_FAST               13 (m)
           2840 LOAD_CONST              37 (37)
           2843 COMPARE_OP               0 (<)
           2846 POP_JUMP_IF_FALSE     2862

334        2849 LOAD_FAST               15 (o)
           2852 LOAD_CONST              18 (1)
           2855 INPLACE_ADD         
           2856 STORE_FAST              15 (o)
           2859 JUMP_FORWARD            10 (to 2872)

336     >> 2862 LOAD_FAST               15 (o)
           2865 LOAD_CONST              37 (37)
           2868 INPLACE_SUBTRACT    
           2869 STORE_FAST              15 (o)

337     >> 2872 LOAD_FAST                8 (h)
           2875 LOAD_CONST              37 (37)
           2878 COMPARE_OP               0 (<)
           2881 POP_JUMP_IF_FALSE     2897

338        2884 LOAD_FAST                4 (d)
           2887 LOAD_CONST              41 (32)
           2890 INPLACE_ADD         
           2891 STORE_FAST               4 (d)
           2894 JUMP_FORWARD            10 (to 2907)

340     >> 2897 LOAD_FAST                4 (d)
           2900 LOAD_CONST              66 (27)
           2903 INPLACE_ADD         
           2904 STORE_FAST               4 (d)

341     >> 2907 LOAD_FAST               14 (n)
           2910 LOAD_CONST              43 (38)
           2913 COMPARE_OP               0 (<)
           2916 POP_JUMP_IF_FALSE     2932

342        2919 LOAD_FAST                4 (d)
           2922 LOAD_CONST              69 (97)
           2925 INPLACE_ADD         
           2926 STORE_FAST               4 (d)
           2929 JUMP_FORWARD            10 (to 2942)

344     >> 2932 LOAD_FAST                4 (d)
           2935 LOAD_CONST              56 (13)
           2938 INPLACE_SUBTRACT    
           2939 STORE_FAST               4 (d)

345     >> 2942 LOAD_FAST                7 (g)
           2945 LOAD_CONST              26 (50)
           2948 COMPARE_OP               0 (<)
           2951 POP_JUMP_IF_FALSE     2967

346        2954 LOAD_FAST                7 (g)
           2957 LOAD_CONST              31 (9)
           2960 INPLACE_ADD         
           2961 STORE_FAST               7 (g)
           2964 JUMP_FORWARD            10 (to 2977)

348     >> 2967 LOAD_FAST                7 (g)
           2970 LOAD_CONST              21 (7)
           2973 INPLACE_SUBTRACT    
           2974 STORE_FAST               7 (g)

349     >> 2977 LOAD_FAST               10 (j)
           2980 LOAD_CONST              70 (43)
           2983 COMPARE_OP               4 (>)
           2986 POP_JUMP_IF_FALSE     3002

350        2989 LOAD_FAST                7 (g)
           2992 LOAD_CONST              12 (6)
           2995 INPLACE_ADD         
           2996 STORE_FAST               7 (g)
           2999 JUMP_FORWARD            10 (to 3012)

352     >> 3002 LOAD_FAST                7 (g)
           3005 LOAD_CONST              42 (48)
           3008 INPLACE_ADD         
           3009 STORE_FAST               7 (g)

353     >> 3012 LOAD_FAST                4 (d)
           3015 LOAD_CONST              25 (34)
           3018 COMPARE_OP               0 (<)
           3021 POP_JUMP_IF_FALSE     3037

354        3024 LOAD_FAST                7 (g)
           3027 LOAD_CONST              67 (26)
           3030 INPLACE_ADD         
           3031 STORE_FAST               7 (g)
           3034 JUMP_FORWARD            10 (to 3047)

356     >> 3037 LOAD_FAST                7 (g)
           3040 LOAD_CONST              53 (12)
           3043 INPLACE_SUBTRACT    
           3044 STORE_FAST               7 (g)

357     >> 3047 LOAD_FAST                2 (b)
           3050 LOAD_CONST              12 (6)
           3053 COMPARE_OP               0 (<)
           3056 POP_JUMP_IF_FALSE     3072

358        3059 LOAD_FAST               18 (r)
           3062 LOAD_CONST              27 (4)
           3065 INPLACE_SUBTRACT    
           3066 STORE_FAST              18 (r)
           3069 JUMP_FORWARD            10 (to 3082)

360     >> 3072 LOAD_FAST               18 (r)
           3075 LOAD_CONST              33 (28)
           3078 INPLACE_ADD         
           3079 STORE_FAST              18 (r)

361     >> 3082 LOAD_FAST               18 (r)
           3085 LOAD_CONST              41 (32)
           3088 COMPARE_OP               4 (>)
           3091 POP_JUMP_IF_FALSE     3107

362        3094 LOAD_FAST               16 (p)
           3097 LOAD_CONST              10 (0)
           3100 INPLACE_ADD         
           3101 STORE_FAST              16 (p)
           3104 JUMP_FORWARD            10 (to 3117)

364     >> 3107 LOAD_FAST               16 (p)
           3110 LOAD_CONST              39 (41)
           3113 INPLACE_ADD         
           3114 STORE_FAST              16 (p)

365     >> 3117 LOAD_FAST               14 (n)
           3120 LOAD_CONST              65 (35)
           3123 COMPARE_OP               4 (>)
           3126 POP_JUMP_IF_FALSE     3142

366        3129 LOAD_FAST                1 (a)
           3132 LOAD_CONST              47 (49)
           3135 INPLACE_ADD         
           3136 STORE_FAST               1 (a)
           3139 JUMP_FORWARD            10 (to 3152)

368     >> 3142 LOAD_FAST                1 (a)
           3145 LOAD_CONST              34 (14)
           3148 INPLACE_SUBTRACT    
           3149 STORE_FAST               1 (a)

369     >> 3152 LOAD_FAST               12 (l)
           3155 LOAD_CONST              40 (30)
           3158 COMPARE_OP               0 (<)
           3161 POP_JUMP_IF_FALSE     3177

370        3164 LOAD_FAST                2 (b)
           3167 LOAD_CONST              63 (36)
           3170 INPLACE_ADD         
           3171 STORE_FAST               2 (b)
           3174 JUMP_FORWARD            10 (to 3187)

372     >> 3177 LOAD_FAST                2 (b)
           3180 LOAD_CONST              10 (0)
           3183 INPLACE_ADD         
           3184 STORE_FAST               2 (b)

373     >> 3187 LOAD_FAST                2 (b)
           3190 LOAD_CONST              40 (30)
           3193 COMPARE_OP               4 (>)
           3196 POP_JUMP_IF_FALSE     3212

374        3199 LOAD_FAST                4 (d)
           3202 LOAD_CONST              63 (36)
           3205 INPLACE_SUBTRACT    
           3206 STORE_FAST               4 (d)
           3209 JUMP_FORWARD            10 (to 3222)

376     >> 3212 LOAD_FAST                4 (d)
           3215 LOAD_CONST              13 (10)
           3218 INPLACE_SUBTRACT    
           3219 STORE_FAST               4 (d)

377     >> 3222 LOAD_FAST                6 (f)
           3225 LOAD_CONST              33 (28)
           3228 COMPARE_OP               0 (<)
           3231 POP_JUMP_IF_FALSE     3247

378        3234 LOAD_FAST               12 (l)
           3237 LOAD_CONST              16 (2)
           3240 INPLACE_ADD         
           3241 STORE_FAST              12 (l)
           3244 JUMP_FORWARD            10 (to 3257)

380     >> 3247 LOAD_FAST               12 (l)
           3250 LOAD_CONST              15 (8)
           3253 INPLACE_SUBTRACT    
           3254 STORE_FAST              12 (l)

381     >> 3257 LOAD_FAST               21 (u)
           3260 LOAD_CONST              41 (32)
           3263 COMPARE_OP               0 (<)
           3266 POP_JUMP_IF_FALSE     3282

382        3269 LOAD_FAST                4 (d)
           3272 LOAD_CONST              39 (41)
           3275 INPLACE_SUBTRACT    
           3276 STORE_FAST               4 (d)
           3279 JUMP_FORWARD            10 (to 3292)

384     >> 3282 LOAD_FAST                4 (d)
           3285 LOAD_CONST              66 (27)
           3288 INPLACE_SUBTRACT    
           3289 STORE_FAST               4 (d)

385     >> 3292 LOAD_FAST                4 (d)
           3295 LOAD_CONST              14 (25)
           3298 COMPARE_OP               4 (>)
           3301 POP_JUMP_IF_FALSE     3317

386        3304 LOAD_FAST               20 (t)
           3307 LOAD_CONST              10 (0)
           3310 INPLACE_ADD         
           3311 STORE_FAST              20 (t)
           3314 JUMP_FORWARD            10 (to 3327)

388     >> 3317 LOAD_FAST               20 (t)
           3320 LOAD_CONST              11 (39)
           3323 INPLACE_SUBTRACT    
           3324 STORE_FAST              20 (t)

389     >> 3327 LOAD_FAST               15 (o)
           3330 LOAD_CONST              61 (47)
           3333 COMPARE_OP               0 (<)
           3336 POP_JUMP_IF_FALSE     3352

390        3339 LOAD_FAST               19 (s)
           3342 LOAD_CONST              10 (0)
           3345 INPLACE_ADD         
           3346 STORE_FAST              19 (s)
           3349 JUMP_FORWARD            10 (to 3362)

392     >> 3352 LOAD_FAST               19 (s)
           3355 LOAD_CONST              61 (47)
           3358 INPLACE_ADD         
           3359 STORE_FAST              19 (s)

393     >> 3362 LOAD_FAST                8 (h)
           3365 LOAD_CONST              61 (47)
           3368 COMPARE_OP               4 (>)
           3371 POP_JUMP_IF_FALSE     3387

394        3374 LOAD_FAST               17 (q)
           3377 LOAD_CONST              31 (9)
           3380 INPLACE_SUBTRACT    
           3381 STORE_FAST              17 (q)
           3384 JUMP_FORWARD            10 (to 3397)

396     >> 3387 LOAD_FAST               17 (q)
           3390 LOAD_CONST              18 (1)
           3393 INPLACE_ADD         
           3394 STORE_FAST              17 (q)

397     >> 3397 LOAD_FAST               20 (t)
           3400 LOAD_CONST              47 (49)
           3403 COMPARE_OP               4 (>)
           3406 POP_JUMP_IF_FALSE     3422

398        3409 LOAD_FAST                3 (c)
           3412 LOAD_CONST              45 (42)
           3415 INPLACE_ADD         
           3416 STORE_FAST               3 (c)
           3419 JUMP_FORWARD            10 (to 3432)

400     >> 3422 LOAD_FAST                3 (c)
           3425 LOAD_CONST              46 (20)
           3428 INPLACE_ADD         
           3429 STORE_FAST               3 (c)

401     >> 3432 LOAD_FAST               11 (k)
           3435 LOAD_CONST              35 (5)
           3438 COMPARE_OP               0 (<)
           3441 POP_JUMP_IF_FALSE     3457

402        3444 LOAD_FAST                8 (h)
           3447 LOAD_CONST              10 (0)
           3450 INPLACE_ADD         
           3451 STORE_FAST               8 (h)
           3454 JUMP_FORWARD            10 (to 3467)

404     >> 3457 LOAD_FAST                8 (h)
           3460 LOAD_CONST              48 (23)
           3463 INPLACE_SUBTRACT    
           3464 STORE_FAST               8 (h)

405     >> 3467 LOAD_FAST                7 (g)
           3470 LOAD_CONST              43 (38)
           3473 COMPARE_OP               0 (<)
           3476 POP_JUMP_IF_FALSE     3492

406        3479 LOAD_FAST               19 (s)
           3482 LOAD_CONST              39 (41)
           3485 INPLACE_ADD         
           3486 STORE_FAST              19 (s)
           3489 JUMP_FORWARD            10 (to 3502)

408     >> 3492 LOAD_FAST               19 (s)
           3495 LOAD_CONST              25 (34)
           3498 INPLACE_ADD         
           3499 STORE_FAST              19 (s)

409     >> 3502 LOAD_FAST               11 (k)
           3505 LOAD_CONST              23 (21)
           3508 COMPARE_OP               4 (>)
           3511 POP_JUMP_IF_FALSE     3527

410        3514 LOAD_FAST               15 (o)
           3517 LOAD_CONST              50 (22)
           3520 INPLACE_ADD         
           3521 STORE_FAST              15 (o)
           3524 JUMP_FORWARD            10 (to 3537)

412     >> 3527 LOAD_FAST               15 (o)
           3530 LOAD_CONST              10 (0)
           3533 INPLACE_ADD         
           3534 STORE_FAST              15 (o)

413     >> 3537 LOAD_FAST               21 (u)
           3540 LOAD_CONST              42 (48)
           3543 COMPARE_OP               4 (>)
           3546 POP_JUMP_IF_FALSE     3562

414        3549 LOAD_FAST               16 (p)
           3552 LOAD_CONST              29 (15)
           3555 INPLACE_SUBTRACT    
           3556 STORE_FAST              16 (p)
           3559 JUMP_FORWARD            10 (to 3572)

416     >> 3562 LOAD_FAST               16 (p)
           3565 LOAD_CONST              71 (73)
           3568 INPLACE_ADD         
           3569 STORE_FAST              16 (p)

417     >> 3572 LOAD_FAST                4 (d)
           3575 LOAD_CONST              27 (4)
           3578 COMPARE_OP               4 (>)
           3581 POP_JUMP_IF_FALSE     3597

418        3584 LOAD_FAST                1 (a)
           3587 LOAD_CONST              18 (1)
           3590 INPLACE_SUBTRACT    
           3591 STORE_FAST               1 (a)
           3594 JUMP_FORWARD            10 (to 3607)

420     >> 3597 LOAD_FAST                1 (a)
           3600 LOAD_CONST              26 (50)
           3603 INPLACE_ADD         
           3604 STORE_FAST               1 (a)

421     >> 3607 LOAD_FAST                8 (h)
           3610 LOAD_CONST              70 (43)
           3613 COMPARE_OP               0 (<)
           3616 POP_JUMP_IF_FALSE     3632

422        3619 LOAD_FAST               14 (n)
           3622 LOAD_CONST              46 (20)
           3625 INPLACE_ADD         
           3626 STORE_FAST              14 (n)
           3629 JUMP_FORWARD            10 (to 3642)

424     >> 3632 LOAD_FAST               14 (n)
           3635 LOAD_CONST              37 (37)
           3638 INPLACE_ADD         
           3639 STORE_FAST              14 (n)

425     >> 3642 LOAD_FAST               13 (m)
           3645 LOAD_CONST              66 (27)
           3648 COMPARE_OP               0 (<)
           3651 POP_JUMP_IF_FALSE     3667

426        3654 LOAD_FAST               20 (t)
           3657 LOAD_CONST              67 (26)
           3660 INPLACE_ADD         
           3661 STORE_FAST              20 (t)
           3664 JUMP_FORWARD            10 (to 3677)

428     >> 3667 LOAD_FAST               20 (t)
           3670 LOAD_CONST              13 (10)
           3673 INPLACE_ADD         
           3674 STORE_FAST              20 (t)

429     >> 3677 LOAD_FAST               12 (l)
           3680 LOAD_CONST              72 (18)
           3683 COMPARE_OP               0 (<)
           3686 POP_JUMP_IF_FALSE     3702

430        3689 LOAD_FAST               16 (p)
           3692 LOAD_CONST              22 (46)
           3695 INPLACE_SUBTRACT    
           3696 STORE_FAST              16 (p)
           3699 JUMP_FORWARD            10 (to 3712)

432     >> 3702 LOAD_FAST               16 (p)
           3705 LOAD_CONST              21 (7)
           3708 INPLACE_SUBTRACT    
           3709 STORE_FAST              16 (p)

433     >> 3712 LOAD_FAST               14 (n)
           3715 LOAD_CONST              12 (6)
           3718 COMPARE_OP               4 (>)
           3721 POP_JUMP_IF_FALSE     3737

434        3724 LOAD_FAST                3 (c)
           3727 LOAD_CONST              18 (1)
           3730 INPLACE_ADD         
           3731 STORE_FAST               3 (c)
           3734 JUMP_FORWARD            10 (to 3747)

436     >> 3737 LOAD_FAST                3 (c)
           3740 LOAD_CONST              65 (35)
           3743 INPLACE_SUBTRACT    
           3744 STORE_FAST               3 (c)

437     >> 3747 LOAD_FAST               17 (q)
           3750 LOAD_CONST              33 (28)
           3753 COMPARE_OP               4 (>)
           3756 POP_JUMP_IF_FALSE     3772

438        3759 LOAD_FAST                6 (f)
           3762 LOAD_CONST              29 (15)
           3765 INPLACE_ADD         
           3766 STORE_FAST               6 (f)
           3769 JUMP_FORWARD            10 (to 3782)

440     >> 3772 LOAD_FAST                6 (f)
           3775 LOAD_CONST              11 (39)
           3778 INPLACE_ADD         
           3779 STORE_FAST               6 (f)

441     >> 3782 LOAD_FAST                5 (e)
           3785 LOAD_CONST              20 (17)
           3788 COMPARE_OP               0 (<)
           3791 POP_JUMP_IF_FALSE     3807

442        3794 LOAD_FAST               21 (u)
           3797 LOAD_CONST              51 (40)
           3800 INPLACE_ADD         
           3801 STORE_FAST              21 (u)
           3804 JUMP_FORWARD            10 (to 3817)

444     >> 3807 LOAD_FAST               21 (u)
           3810 LOAD_CONST              29 (15)
           3813 INPLACE_ADD         
           3814 STORE_FAST              21 (u)

445     >> 3817 LOAD_FAST               13 (m)
           3820 LOAD_CONST              42 (48)
           3823 COMPARE_OP               0 (<)
           3826 POP_JUMP_IF_FALSE     3842

446        3829 LOAD_FAST                4 (d)
           3832 LOAD_CONST              72 (18)
           3835 INPLACE_SUBTRACT    
           3836 STORE_FAST               4 (d)
           3839 JUMP_FORWARD            10 (to 3852)

448     >> 3842 LOAD_FAST                4 (d)
           3845 LOAD_CONST              32 (45)
           3848 INPLACE_SUBTRACT    
           3849 STORE_FAST               4 (d)

449     >> 3852 LOAD_FAST               16 (p)
           3855 LOAD_CONST              12 (6)
           3858 COMPARE_OP               4 (>)
           3861 POP_JUMP_IF_FALSE     3877

450        3864 LOAD_FAST                3 (c)
           3867 LOAD_CONST              51 (40)
           3870 INPLACE_ADD         
           3871 STORE_FAST               3 (c)
           3874 JUMP_FORWARD            10 (to 3887)

452     >> 3877 LOAD_FAST                3 (c)
           3880 LOAD_CONST              53 (12)
           3883 INPLACE_ADD         
           3884 STORE_FAST               3 (c)

453     >> 3887 LOAD_FAST                1 (a)
           3890 LOAD_CONST              14 (25)
           3893 COMPARE_OP               4 (>)
           3896 POP_JUMP_IF_FALSE     3912

454        3899 LOAD_FAST                9 (i)
           3902 LOAD_CONST              16 (2)
           3905 INPLACE_SUBTRACT    
           3906 STORE_FAST               9 (i)
           3909 JUMP_FORWARD            10 (to 3922)

456     >> 3912 LOAD_FAST                9 (i)
           3915 LOAD_CONST              24 (31)
           3918 INPLACE_SUBTRACT    
           3919 STORE_FAST               9 (i)

457     >> 3922 LOAD_FAST                7 (g)
           3925 LOAD_CONST              29 (15)
           3928 COMPARE_OP               4 (>)
           3931 POP_JUMP_IF_FALSE     3947

458        3934 LOAD_FAST               13 (m)
           3937 LOAD_CONST              46 (20)
           3940 INPLACE_ADD         
           3941 STORE_FAST              13 (m)
           3944 JUMP_FORWARD            10 (to 3957)

460     >> 3947 LOAD_FAST               13 (m)
           3950 LOAD_CONST              26 (50)
           3953 INPLACE_ADD         
           3954 STORE_FAST              13 (m)

461     >> 3957 LOAD_FAST                4 (d)
           3960 LOAD_CONST              55 (44)
           3963 COMPARE_OP               0 (<)
           3966 POP_JUMP_IF_FALSE     3982

462        3969 LOAD_FAST                1 (a)
           3972 LOAD_CONST              21 (7)
           3975 INPLACE_ADD         
           3976 STORE_FAST               1 (a)
           3979 JUMP_FORWARD            10 (to 3992)

464     >> 3982 LOAD_FAST                1 (a)
           3985 LOAD_CONST              18 (1)
           3988 INPLACE_SUBTRACT    
           3989 STORE_FAST               1 (a)

465     >> 3992 LOAD_FAST               14 (n)
           3995 LOAD_CONST              21 (7)
           3998 COMPARE_OP               4 (>)
           4001 POP_JUMP_IF_FALSE     4017

466        4004 LOAD_FAST                9 (i)
           4007 LOAD_CONST              72 (18)
           4010 INPLACE_SUBTRACT    
           4011 STORE_FAST               9 (i)
           4014 JUMP_FORWARD            10 (to 4027)

468     >> 4017 LOAD_FAST                9 (i)
           4020 LOAD_CONST              21 (7)
           4023 INPLACE_ADD         
           4024 STORE_FAST               9 (i)

469     >> 4027 LOAD_FAST               18 (r)
           4030 LOAD_CONST              17 (24)
           4033 COMPARE_OP               4 (>)
           4036 POP_JUMP_IF_FALSE     4052

470        4039 LOAD_FAST               15 (o)
           4042 LOAD_CONST              73 (87)
           4045 INPLACE_ADD         
           4046 STORE_FAST              15 (o)
           4049 JUMP_FORWARD            10 (to 4062)

472     >> 4052 LOAD_FAST               15 (o)
           4055 LOAD_CONST              63 (36)
           4058 INPLACE_ADD         
           4059 STORE_FAST              15 (o)

473     >> 4062 LOAD_FAST               10 (j)
           4065 LOAD_CONST              13 (10)
           4068 COMPARE_OP               0 (<)
           4071 POP_JUMP_IF_FALSE     4087

474        4074 LOAD_FAST               16 (p)
           4077 LOAD_CONST              25 (34)
           4080 INPLACE_ADD         
           4081 STORE_FAST              16 (p)
           4084 JUMP_FORWARD            10 (to 4097)

476     >> 4087 LOAD_FAST               16 (p)
           4090 LOAD_CONST              74 (196)
           4093 INPLACE_ADD         
           4094 STORE_FAST              16 (p)

477     >> 4097 LOAD_FAST                1 (a)
           4100 LOAD_CONST              26 (50)
           4103 COMPARE_OP               0 (<)
           4106 POP_JUMP_IF_FALSE     4122

478        4109 LOAD_FAST               14 (n)
           4112 LOAD_CONST              17 (24)
           4115 INPLACE_ADD         
           4116 STORE_FAST              14 (n)
           4119 JUMP_FORWARD            10 (to 4132)

480     >> 4122 LOAD_FAST               14 (n)
           4125 LOAD_CONST              19 (3)
           4128 INPLACE_SUBTRACT    
           4129 STORE_FAST              14 (n)

481     >> 4132 LOAD_FAST                6 (f)
           4135 LOAD_CONST              10 (0)
           4138 COMPARE_OP               0 (<)
           4141 POP_JUMP_IF_FALSE     4157

482        4144 LOAD_FAST                1 (a)
           4147 LOAD_CONST              47 (49)
           4150 INPLACE_ADD         
           4151 STORE_FAST               1 (a)
           4154 JUMP_FORWARD            10 (to 4167)

484     >> 4157 LOAD_FAST                1 (a)
           4160 LOAD_CONST              35 (5)
           4163 INPLACE_ADD         
           4164 STORE_FAST               1 (a)

485     >> 4167 LOAD_FAST                8 (h)
           4170 LOAD_CONST              24 (31)
           4173 COMPARE_OP               0 (<)
           4176 POP_JUMP_IF_FALSE     4192

486        4179 LOAD_FAST                4 (d)
           4182 LOAD_CONST              43 (38)
           4185 INPLACE_SUBTRACT    
           4186 STORE_FAST               4 (d)
           4189 JUMP_FORWARD            10 (to 4202)

488     >> 4192 LOAD_FAST                4 (d)
           4195 LOAD_CONST              39 (41)
           4198 INPLACE_SUBTRACT    
           4199 STORE_FAST               4 (d)

489     >> 4202 LOAD_FAST               16 (p)
           4205 LOAD_CONST              42 (48)
           4208 COMPARE_OP               0 (<)
           4211 POP_JUMP_IF_FALSE     4227

490        4214 LOAD_FAST               15 (o)
           4217 LOAD_CONST              26 (50)
           4220 INPLACE_SUBTRACT    
           4221 STORE_FAST              15 (o)
           4224 JUMP_FORWARD            10 (to 4237)

492     >> 4227 LOAD_FAST               15 (o)
           4230 LOAD_CONST              10 (0)
           4233 INPLACE_ADD         
           4234 STORE_FAST              15 (o)

493     >> 4237 LOAD_FAST               21 (u)
           4240 LOAD_CONST              50 (22)
           4243 COMPARE_OP               4 (>)
           4246 POP_JUMP_IF_FALSE     4262

494        4249 LOAD_FAST                3 (c)
           4252 LOAD_CONST              55 (44)
           4255 INPLACE_ADD         
           4256 STORE_FAST               3 (c)
           4259 JUMP_FORWARD            10 (to 4272)

496     >> 4262 LOAD_FAST                3 (c)
           4265 LOAD_CONST              40 (30)
           4268 INPLACE_SUBTRACT    
           4269 STORE_FAST               3 (c)

497     >> 4272 LOAD_FAST                2 (b)
           4275 LOAD_CONST              12 (6)
           4278 COMPARE_OP               4 (>)
           4281 POP_JUMP_IF_FALSE     4297

498        4284 LOAD_FAST                3 (c)
           4287 LOAD_CONST              41 (32)
           4290 INPLACE_SUBTRACT    
           4291 STORE_FAST               3 (c)
           4294 JUMP_FORWARD            10 (to 4307)

500     >> 4297 LOAD_FAST                3 (c)
           4300 LOAD_CONST              13 (10)
           4303 INPLACE_ADD         
           4304 STORE_FAST               3 (c)

501     >> 4307 LOAD_FAST                4 (d)
           4310 LOAD_CONST              56 (13)
           4313 COMPARE_OP               4 (>)
           4316 POP_JUMP_IF_FALSE     4332

502        4319 LOAD_FAST               15 (o)
           4322 LOAD_CONST              16 (2)
           4325 INPLACE_SUBTRACT    
           4326 STORE_FAST              15 (o)
           4329 JUMP_FORWARD            10 (to 4342)

504     >> 4332 LOAD_FAST               15 (o)
           4335 LOAD_CONST              41 (32)
           4338 INPLACE_SUBTRACT    
           4339 STORE_FAST              15 (o)

505     >> 4342 LOAD_FAST                1 (a)
           4345 LOAD_CONST              34 (14)
           4348 COMPARE_OP               4 (>)
           4351 POP_JUMP_IF_FALSE     4367

506        4354 LOAD_FAST               14 (n)
           4357 LOAD_CONST              55 (44)
           4360 INPLACE_ADD         
           4361 STORE_FAST              14 (n)
           4364 JUMP_FORWARD            10 (to 4377)

508     >> 4367 LOAD_FAST               14 (n)
           4370 LOAD_CONST              20 (17)
           4373 INPLACE_ADD         
           4374 STORE_FAST              14 (n)

509     >> 4377 LOAD_FAST               18 (r)
           4380 LOAD_CONST              29 (15)
           4383 COMPARE_OP               0 (<)
           4386 POP_JUMP_IF_FALSE     4402

510        4389 LOAD_FAST                3 (c)
           4392 LOAD_CONST              35 (5)
           4395 INPLACE_SUBTRACT    
           4396 STORE_FAST               3 (c)
           4399 JUMP_FORWARD            10 (to 4412)

512     >> 4402 LOAD_FAST                3 (c)
           4405 LOAD_CONST              10 (0)
           4408 INPLACE_ADD         
           4409 STORE_FAST               3 (c)

513     >> 4412 LOAD_FAST               10 (j)
           4415 LOAD_CONST              41 (32)
           4418 COMPARE_OP               4 (>)
           4421 POP_JUMP_IF_FALSE     4437

514        4424 LOAD_FAST               12 (l)
           4427 LOAD_CONST              13 (10)
           4430 INPLACE_SUBTRACT    
           4431 STORE_FAST              12 (l)
           4434 JUMP_FORWARD            10 (to 4447)

516     >> 4437 LOAD_FAST               12 (l)
           4440 LOAD_CONST              37 (37)
           4443 INPLACE_ADD         
           4444 STORE_FAST              12 (l)

517     >> 4447 LOAD_FAST                8 (h)
           4450 LOAD_CONST              30 (19)
           4453 COMPARE_OP               4 (>)
           4456 POP_JUMP_IF_FALSE     4472

518        4459 LOAD_FAST                6 (f)
           4462 LOAD_CONST              48 (23)
           4465 INPLACE_ADD         
           4466 STORE_FAST               6 (f)
           4469 JUMP_FORWARD            10 (to 4482)

520     >> 4472 LOAD_FAST                6 (f)
           4475 LOAD_CONST              75 (309)
           4478 INPLACE_ADD         
           4479 STORE_FAST               6 (f)

521     >> 4482 LOAD_FAST               18 (r)
           4485 LOAD_CONST              43 (38)
           4488 COMPARE_OP               0 (<)
           4491 POP_JUMP_IF_FALSE     4507

522        4494 LOAD_FAST               21 (u)
           4497 LOAD_CONST              33 (28)
           4500 INPLACE_ADD         
           4501 STORE_FAST              21 (u)
           4504 JUMP_FORWARD            10 (to 4517)

524     >> 4507 LOAD_FAST               21 (u)
           4510 LOAD_CONST              35 (5)
           4513 INPLACE_SUBTRACT    
           4514 STORE_FAST              21 (u)

525     >> 4517 LOAD_FAST               20 (t)
           4520 LOAD_CONST              39 (41)
           4523 COMPARE_OP               4 (>)
           4526 POP_JUMP_IF_FALSE     4542

526        4529 LOAD_FAST                4 (d)
           4532 LOAD_CONST              11 (39)
           4535 INPLACE_ADD         
           4536 STORE_FAST               4 (d)
           4539 JUMP_FORWARD            10 (to 4552)

528     >> 4542 LOAD_FAST                4 (d)
           4545 LOAD_CONST              70 (43)
           4548 INPLACE_ADD         
           4549 STORE_FAST               4 (d)

529     >> 4552 LOAD_FAST               11 (k)
           4555 LOAD_CONST              25 (34)
           4558 COMPARE_OP               4 (>)
           4561 POP_JUMP_IF_FALSE     4577

530        4564 LOAD_FAST               17 (q)
           4567 LOAD_CONST              24 (31)
           4570 INPLACE_SUBTRACT    
           4571 STORE_FAST              17 (q)
           4574 JUMP_FORWARD            10 (to 4587)

532     >> 4577 LOAD_FAST               17 (q)
           4580 LOAD_CONST              49 (11)
           4583 INPLACE_SUBTRACT    
           4584 STORE_FAST              17 (q)

533     >> 4587 LOAD_FAST               15 (o)
           4590 LOAD_CONST              18 (1)
           4593 COMPARE_OP               0 (<)
           4596 POP_JUMP_IF_FALSE     4612

534        4599 LOAD_FAST                7 (g)
           4602 LOAD_CONST              44 (33)
           4605 INPLACE_ADD         
           4606 STORE_FAST               7 (g)
           4609 JUMP_FORWARD            10 (to 4622)

536     >> 4612 LOAD_FAST                7 (g)
           4615 LOAD_CONST              12 (6)
           4618 INPLACE_ADD         
           4619 STORE_FAST               7 (g)

537     >> 4622 LOAD_FAST               17 (q)
           4625 LOAD_CONST              31 (9)
           4628 COMPARE_OP               0 (<)
           4631 POP_JUMP_IF_FALSE     4647

538        4634 LOAD_FAST                5 (e)
           4637 LOAD_CONST              44 (33)
           4640 INPLACE_SUBTRACT    
           4641 STORE_FAST               5 (e)
           4644 JUMP_FORWARD            10 (to 4657)

540     >> 4647 LOAD_FAST                5 (e)
           4650 LOAD_CONST              31 (9)
           4653 INPLACE_ADD         
           4654 STORE_FAST               5 (e)

541     >> 4657 LOAD_FAST                6 (f)
           4660 LOAD_CONST              35 (5)
           4663 COMPARE_OP               4 (>)
           4666 POP_JUMP_IF_FALSE     4682

542        4669 LOAD_FAST               11 (k)
           4672 LOAD_CONST              76 (79)
           4675 INPLACE_ADD         
           4676 STORE_FAST              11 (k)
           4679 JUMP_FORWARD            10 (to 4692)

544     >> 4682 LOAD_FAST               11 (k)
           4685 LOAD_CONST              70 (43)
           4688 INPLACE_ADD         
           4689 STORE_FAST              11 (k)

545     >> 4692 LOAD_FAST               13 (m)
           4695 LOAD_CONST              17 (24)
           4698 COMPARE_OP               4 (>)
           4701 POP_JUMP_IF_FALSE     4717

546        4704 LOAD_FAST                6 (f)
           4707 LOAD_CONST              77 (119)
           4710 INPLACE_SUBTRACT    
           4711 STORE_FAST               6 (f)
           4714 JUMP_FORWARD            10 (to 4727)

548     >> 4717 LOAD_FAST                6 (f)
           4720 LOAD_CONST              32 (45)
           4723 INPLACE_ADD         
           4724 STORE_FAST               6 (f)

549     >> 4727 LOAD_FAST                2 (b)
           4730 LOAD_CONST              25 (34)
           4733 COMPARE_OP               4 (>)
           4736 POP_JUMP_IF_FALSE     4752

550        4739 LOAD_FAST                5 (e)
           4742 LOAD_CONST              22 (46)
           4745 INPLACE_SUBTRACT    
           4746 STORE_FAST               5 (e)
           4749 JUMP_FORWARD            10 (to 4762)

552     >> 4752 LOAD_FAST                5 (e)
           4755 LOAD_CONST              35 (5)
           4758 INPLACE_ADD         
           4759 STORE_FAST               5 (e)

553     >> 4762 LOAD_FAST               13 (m)
           4765 LOAD_CONST              50 (22)
           4768 COMPARE_OP               4 (>)
           4771 POP_JUMP_IF_FALSE     4787

554        4774 LOAD_FAST                9 (i)
           4777 LOAD_CONST              15 (8)
           4780 INPLACE_ADD         
           4781 STORE_FAST               9 (i)
           4784 JUMP_FORWARD            10 (to 4797)

556     >> 4787 LOAD_FAST                9 (i)
           4790 LOAD_CONST              50 (22)
           4793 INPLACE_ADD         
           4794 STORE_FAST               9 (i)

557     >> 4797 LOAD_FAST                6 (f)
           4800 LOAD_CONST              24 (31)
           4803 COMPARE_OP               4 (>)
           4806 POP_JUMP_IF_FALSE     4822

558        4809 LOAD_FAST                6 (f)
           4812 LOAD_CONST              18 (1)
           4815 INPLACE_ADD         
           4816 STORE_FAST               6 (f)
           4819 JUMP_FORWARD            10 (to 4832)

560     >> 4822 LOAD_FAST                6 (f)
           4825 LOAD_CONST              66 (27)
           4828 INPLACE_ADD         
           4829 STORE_FAST               6 (f)

561     >> 4832 LOAD_FAST               15 (o)
           4835 LOAD_CONST              18 (1)
           4838 COMPARE_OP               0 (<)
           4841 POP_JUMP_IF_FALSE     4857

562        4844 LOAD_FAST                2 (b)
           4847 LOAD_CONST              14 (25)
           4850 INPLACE_SUBTRACT    
           4851 STORE_FAST               2 (b)
           4854 JUMP_FORWARD            10 (to 4867)

564     >> 4857 LOAD_FAST                2 (b)
           4860 LOAD_CONST              18 (1)
           4863 INPLACE_SUBTRACT    
           4864 STORE_FAST               2 (b)

565     >> 4867 LOAD_FAST               10 (j)
           4870 LOAD_CONST              67 (26)
           4873 COMPARE_OP               4 (>)
           4876 POP_JUMP_IF_FALSE     4892

566        4879 LOAD_FAST                5 (e)
           4882 LOAD_CONST              21 (7)
           4885 INPLACE_ADD         
           4886 STORE_FAST               5 (e)
           4889 JUMP_FORWARD            10 (to 4902)

568     >> 4892 LOAD_FAST                5 (e)
           4895 LOAD_CONST              32 (45)
           4898 INPLACE_SUBTRACT    
           4899 STORE_FAST               5 (e)

569     >> 4902 LOAD_FAST                1 (a)
           4905 LOAD_CONST              41 (32)
           4908 COMPARE_OP               4 (>)
           4911 POP_JUMP_IF_FALSE     4927

570        4914 LOAD_FAST                6 (f)
           4917 LOAD_CONST              78 (77)
           4920 INPLACE_SUBTRACT    
           4921 STORE_FAST               6 (f)
           4924 JUMP_FORWARD            10 (to 4937)

572     >> 4927 LOAD_FAST                6 (f)
           4930 LOAD_CONST              43 (38)
           4933 INPLACE_SUBTRACT    
           4934 STORE_FAST               6 (f)

573     >> 4937 LOAD_FAST               15 (o)
           4940 LOAD_CONST              17 (24)
           4943 COMPARE_OP               0 (<)
           4946 POP_JUMP_IF_FALSE     4962

574        4949 LOAD_FAST                6 (f)
           4952 LOAD_CONST              41 (32)
           4955 INPLACE_SUBTRACT    
           4956 STORE_FAST               6 (f)
           4959 JUMP_FORWARD            10 (to 4972)

576     >> 4962 LOAD_FAST                6 (f)
           4965 LOAD_CONST              19 (3)
           4968 INPLACE_SUBTRACT    
           4969 STORE_FAST               6 (f)

577     >> 4972 LOAD_FAST               15 (o)
           4975 LOAD_CONST              46 (20)
           4978 COMPARE_OP               0 (<)
           4981 POP_JUMP_IF_FALSE     4997

578        4984 LOAD_FAST                6 (f)
           4987 LOAD_CONST              24 (31)
           4990 INPLACE_ADD         
           4991 STORE_FAST               6 (f)
           4994 JUMP_FORWARD            10 (to 5007)

580     >> 4997 LOAD_FAST                6 (f)
           5000 LOAD_CONST              19 (3)
           5003 INPLACE_ADD         
           5004 STORE_FAST               6 (f)

581     >> 5007 LOAD_FAST               19 (s)
           5010 LOAD_CONST              43 (38)
           5013 COMPARE_OP               4 (>)
           5016 POP_JUMP_IF_FALSE     5032

582        5019 LOAD_FAST               21 (u)
           5022 LOAD_CONST              79 (80)
           5025 INPLACE_ADD         
           5026 STORE_FAST              21 (u)
           5029 JUMP_FORWARD            10 (to 5042)

584     >> 5032 LOAD_FAST               21 (u)
           5035 LOAD_CONST              67 (26)
           5038 INPLACE_SUBTRACT    
           5039 STORE_FAST              21 (u)

585     >> 5042 LOAD_FAST                8 (h)
           5045 LOAD_CONST              72 (18)
           5048 COMPARE_OP               0 (<)
           5051 POP_JUMP_IF_FALSE     5067

586        5054 LOAD_FAST                2 (b)
           5057 LOAD_CONST              72 (18)
           5060 INPLACE_ADD         
           5061 STORE_FAST               2 (b)
           5064 JUMP_FORWARD            10 (to 5077)

588     >> 5067 LOAD_FAST                2 (b)
           5070 LOAD_CONST              23 (21)
           5073 INPLACE_SUBTRACT    
           5074 STORE_FAST               2 (b)

589     >> 5077 LOAD_FAST               21 (u)
           5080 LOAD_CONST              33 (28)
           5083 COMPARE_OP               4 (>)
           5086 POP_JUMP_IF_FALSE     5102

590        5089 LOAD_FAST               19 (s)
           5092 LOAD_CONST              10 (0)
           5095 INPLACE_ADD         
           5096 STORE_FAST              19 (s)
           5099 JUMP_FORWARD            10 (to 5112)

592     >> 5102 LOAD_FAST               19 (s)
           5105 LOAD_CONST              52 (16)
           5108 INPLACE_ADD         
           5109 STORE_FAST              19 (s)

593     >> 5112 LOAD_FAST               21 (u)
           5115 LOAD_CONST              17 (24)
           5118 COMPARE_OP               4 (>)
           5121 POP_JUMP_IF_FALSE     5137

594        5124 LOAD_FAST               17 (q)
           5127 LOAD_CONST              31 (9)
           5130 INPLACE_SUBTRACT    
           5131 STORE_FAST              17 (q)
           5134 JUMP_FORWARD            10 (to 5147)

596     >> 5137 LOAD_FAST               17 (q)
           5140 LOAD_CONST              53 (12)
           5143 INPLACE_ADD         
           5144 STORE_FAST              17 (q)

597     >> 5147 LOAD_FAST                6 (f)
           5150 LOAD_CONST              13 (10)
           5153 COMPARE_OP               0 (<)
           5156 POP_JUMP_IF_FALSE     5172

598        5159 LOAD_FAST               12 (l)
           5162 LOAD_CONST              65 (35)
           5165 INPLACE_SUBTRACT    
           5166 STORE_FAST              12 (l)
           5169 JUMP_FORWARD            10 (to 5182)

600     >> 5172 LOAD_FAST               12 (l)
           5175 LOAD_CONST              29 (15)
           5178 INPLACE_ADD         
           5179 STORE_FAST              12 (l)

601     >> 5182 LOAD_FAST               13 (m)
           5185 LOAD_CONST              26 (50)
           5188 COMPARE_OP               0 (<)
           5191 POP_JUMP_IF_FALSE     5207

602        5194 LOAD_FAST               17 (q)
           5197 LOAD_CONST              44 (33)
           5200 INPLACE_SUBTRACT    
           5201 STORE_FAST              17 (q)
           5204 JUMP_FORWARD            10 (to 5217)

604     >> 5207 LOAD_FAST               17 (q)
           5210 LOAD_CONST              65 (35)
           5213 INPLACE_ADD         
           5214 STORE_FAST              17 (q)

605     >> 5217 LOAD_FAST               16 (p)
           5220 LOAD_CONST              41 (32)
           5223 COMPARE_OP               0 (<)
           5226 POP_JUMP_IF_FALSE     5242

606        5229 LOAD_FAST                8 (h)
           5232 LOAD_CONST              33 (28)
           5235 INPLACE_ADD         
           5236 STORE_FAST               8 (h)
           5239 JUMP_FORWARD            10 (to 5252)

608     >> 5242 LOAD_FAST                8 (h)
           5245 LOAD_CONST              80 (127)
           5248 INPLACE_ADD         
           5249 STORE_FAST               8 (h)

609     >> 5252 LOAD_FAST               20 (t)
           5255 LOAD_CONST              49 (11)
           5258 COMPARE_OP               0 (<)
           5261 POP_JUMP_IF_FALSE     5277

610        5264 LOAD_FAST                6 (f)
           5267 LOAD_CONST              16 (2)
           5270 INPLACE_ADD         
           5271 STORE_FAST               6 (f)
           5274 JUMP_FORWARD            10 (to 5287)

612     >> 5277 LOAD_FAST                6 (f)
           5280 LOAD_CONST              53 (12)
           5283 INPLACE_SUBTRACT    
           5284 STORE_FAST               6 (f)

613     >> 5287 LOAD_FAST               14 (n)
           5290 LOAD_CONST              46 (20)
           5293 COMPARE_OP               0 (<)
           5296 POP_JUMP_IF_FALSE     5312

614        5299 LOAD_FAST               17 (q)
           5302 LOAD_CONST              50 (22)
           5305 INPLACE_ADD         
           5306 STORE_FAST              17 (q)
           5309 JUMP_FORWARD            10 (to 5322)

616     >> 5312 LOAD_FAST               17 (q)
           5315 LOAD_CONST              31 (9)
           5318 INPLACE_SUBTRACT    
           5319 STORE_FAST              17 (q)

617     >> 5322 LOAD_FAST               21 (u)
           5325 LOAD_CONST              46 (20)
           5328 COMPARE_OP               4 (>)
           5331 POP_JUMP_IF_FALSE     5347

618        5334 LOAD_FAST               14 (n)
           5337 LOAD_CONST              31 (9)
           5340 INPLACE_ADD         
           5341 STORE_FAST              14 (n)
           5344 JUMP_FORWARD            10 (to 5357)

620     >> 5347 LOAD_FAST               14 (n)
           5350 LOAD_CONST              37 (37)
           5353 INPLACE_ADD         
           5354 STORE_FAST              14 (n)

621     >> 5357 LOAD_FAST                7 (g)
           5360 LOAD_CONST              47 (49)
           5363 COMPARE_OP               4 (>)
           5366 POP_JUMP_IF_FALSE     5382

622        5369 LOAD_FAST                7 (g)
           5372 LOAD_CONST              63 (36)
           5375 INPLACE_ADD         
           5376 STORE_FAST               7 (g)
           5379 JUMP_FORWARD            10 (to 5392)

624     >> 5382 LOAD_FAST                7 (g)
           5385 LOAD_CONST              14 (25)
           5388 INPLACE_ADD         
           5389 STORE_FAST               7 (g)

625     >> 5392 LOAD_FAST               20 (t)
           5395 LOAD_CONST              24 (31)
           5398 COMPARE_OP               0 (<)
           5401 POP_JUMP_IF_FALSE     5417

626        5404 LOAD_FAST               19 (s)
           5407 LOAD_CONST              39 (41)
           5410 INPLACE_SUBTRACT    
           5411 STORE_FAST              19 (s)
           5414 JUMP_FORWARD            10 (to 5427)

628     >> 5417 LOAD_FAST               19 (s)
           5420 LOAD_CONST              48 (23)
           5423 INPLACE_ADD         
           5424 STORE_FAST              19 (s)

629     >> 5427 LOAD_FAST                2 (b)
           5430 LOAD_CONST              14 (25)
           5433 COMPARE_OP               0 (<)
           5436 POP_JUMP_IF_FALSE     5452

630        5439 LOAD_FAST                2 (b)
           5442 LOAD_CONST              81 (68)
           5445 INPLACE_ADD         
           5446 STORE_FAST               2 (b)
           5449 JUMP_FORWARD            10 (to 5462)

632     >> 5452 LOAD_FAST                2 (b)
           5455 LOAD_CONST              41 (32)
           5458 INPLACE_ADD         
           5459 STORE_FAST               2 (b)

633     >> 5462 LOAD_FAST               18 (r)
           5465 LOAD_CONST              52 (16)
           5468 COMPARE_OP               4 (>)
           5471 POP_JUMP_IF_FALSE     5487

634        5474 LOAD_FAST               13 (m)
           5477 LOAD_CONST              56 (13)
           5480 INPLACE_SUBTRACT    
           5481 STORE_FAST              13 (m)
           5484 JUMP_FORWARD            10 (to 5497)

636     >> 5487 LOAD_FAST               13 (m)
           5490 LOAD_CONST              45 (42)
           5493 INPLACE_ADD         
           5494 STORE_FAST              13 (m)

637     >> 5497 LOAD_FAST               18 (r)
           5500 LOAD_CONST              51 (40)
           5503 COMPARE_OP               0 (<)
           5506 POP_JUMP_IF_FALSE     5522

638        5509 LOAD_FAST                1 (a)
           5512 LOAD_CONST              20 (17)
           5515 INPLACE_SUBTRACT    
           5516 STORE_FAST               1 (a)
           5519 JUMP_FORWARD            10 (to 5532)

640     >> 5522 LOAD_FAST                1 (a)
           5525 LOAD_CONST              18 (1)
           5528 INPLACE_ADD         
           5529 STORE_FAST               1 (a)

641     >> 5532 LOAD_FAST                4 (d)
           5535 LOAD_CONST              40 (30)
           5538 COMPARE_OP               0 (<)
           5541 POP_JUMP_IF_FALSE     5557

642        5544 LOAD_FAST               18 (r)
           5547 LOAD_CONST              35 (5)
           5550 INPLACE_SUBTRACT    
           5551 STORE_FAST              18 (r)
           5554 JUMP_FORWARD            10 (to 5567)

644     >> 5557 LOAD_FAST               18 (r)
           5560 LOAD_CONST              15 (8)
           5563 INPLACE_ADD         
           5564 STORE_FAST              18 (r)

645     >> 5567 LOAD_FAST               20 (t)
           5570 LOAD_CONST              18 (1)
           5573 COMPARE_OP               0 (<)
           5576 POP_JUMP_IF_FALSE     5592

646        5579 LOAD_FAST               11 (k)
           5582 LOAD_CONST              49 (11)
           5585 INPLACE_SUBTRACT    
           5586 STORE_FAST              11 (k)
           5589 JUMP_FORWARD            10 (to 5602)

648     >> 5592 LOAD_FAST               11 (k)
           5595 LOAD_CONST              79 (80)
           5598 INPLACE_ADD         
           5599 STORE_FAST              11 (k)

649     >> 5602 LOAD_FAST                3 (c)
           5605 LOAD_CONST              40 (30)
           5608 COMPARE_OP               0 (<)
           5611 POP_JUMP_IF_FALSE     5627

650        5614 LOAD_FAST                7 (g)
           5617 LOAD_CONST              45 (42)
           5620 INPLACE_ADD         
           5621 STORE_FAST               7 (g)
           5624 JUMP_FORWARD            10 (to 5637)

652     >> 5627 LOAD_FAST                7 (g)
           5630 LOAD_CONST              18 (1)
           5633 INPLACE_SUBTRACT    
           5634 STORE_FAST               7 (g)

653     >> 5637 LOAD_FAST               11 (k)
           5640 LOAD_CONST              47 (49)
           5643 COMPARE_OP               4 (>)
           5646 POP_JUMP_IF_FALSE     5662

654        5649 LOAD_FAST                4 (d)
           5652 LOAD_CONST              16 (2)
           5655 INPLACE_SUBTRACT    
           5656 STORE_FAST               4 (d)
           5659 JUMP_FORWARD            10 (to 5672)

656     >> 5662 LOAD_FAST                4 (d)
           5665 LOAD_CONST              65 (35)
           5668 INPLACE_SUBTRACT    
           5669 STORE_FAST               4 (d)

657     >> 5672 LOAD_FAST               13 (m)
           5675 LOAD_CONST              39 (41)
           5678 COMPARE_OP               4 (>)
           5681 POP_JUMP_IF_FALSE     5697

658        5684 LOAD_FAST               16 (p)
           5687 LOAD_CONST              35 (5)
           5690 INPLACE_SUBTRACT    
           5691 STORE_FAST              16 (p)
           5694 JUMP_FORWARD            10 (to 5707)

660     >> 5697 LOAD_FAST               16 (p)
           5700 LOAD_CONST              44 (33)
           5703 INPLACE_SUBTRACT    
           5704 STORE_FAST              16 (p)

661     >> 5707 LOAD_FAST                3 (c)
           5710 LOAD_CONST              39 (41)
           5713 COMPARE_OP               4 (>)
           5716 POP_JUMP_IF_FALSE     5732

662        5719 LOAD_FAST               17 (q)
           5722 LOAD_CONST              12 (6)
           5725 INPLACE_ADD         
           5726 STORE_FAST              17 (q)
           5729 JUMP_FORWARD            10 (to 5742)

664     >> 5732 LOAD_FAST               17 (q)
           5735 LOAD_CONST              52 (16)
           5738 INPLACE_ADD         
           5739 STORE_FAST              17 (q)

665     >> 5742 LOAD_FAST               15 (o)
           5745 LOAD_CONST              27 (4)
           5748 COMPARE_OP               4 (>)
           5751 POP_JUMP_IF_FALSE     5767

666        5754 LOAD_FAST               13 (m)
           5757 LOAD_CONST              29 (15)
           5760 INPLACE_ADD         
           5761 STORE_FAST              13 (m)
           5764 JUMP_FORWARD            10 (to 5777)

668     >> 5767 LOAD_FAST               13 (m)
           5770 LOAD_CONST              44 (33)
           5773 INPLACE_SUBTRACT    
           5774 STORE_FAST              13 (m)

669     >> 5777 LOAD_FAST                2 (b)
           5780 LOAD_CONST              44 (33)
           5783 COMPARE_OP               4 (>)
           5786 POP_JUMP_IF_FALSE     5802

670        5789 LOAD_FAST               13 (m)
           5792 LOAD_CONST              82 (111)
           5795 INPLACE_ADD         
           5796 STORE_FAST              13 (m)
           5799 JUMP_FORWARD            10 (to 5812)

672     >> 5802 LOAD_FAST               13 (m)
           5805 LOAD_CONST              18 (1)
           5808 INPLACE_SUBTRACT    
           5809 STORE_FAST              13 (m)

673     >> 5812 LOAD_FAST                3 (c)
           5815 LOAD_CONST              47 (49)
           5818 COMPARE_OP               0 (<)
           5821 POP_JUMP_IF_FALSE     5837

674        5824 LOAD_FAST                9 (i)
           5827 LOAD_CONST              19 (3)
           5830 INPLACE_ADD         
           5831 STORE_FAST               9 (i)
           5834 JUMP_FORWARD            10 (to 5847)

676     >> 5837 LOAD_FAST                9 (i)
           5840 LOAD_CONST              34 (14)
           5843 INPLACE_ADD         
           5844 STORE_FAST               9 (i)

677     >> 5847 LOAD_FAST                9 (i)
           5850 LOAD_CONST              33 (28)
           5853 COMPARE_OP               4 (>)
           5856 POP_JUMP_IF_FALSE     5872

678        5859 LOAD_FAST                8 (h)
           5862 LOAD_CONST              34 (14)
           5865 INPLACE_ADD         
           5866 STORE_FAST               8 (h)
           5869 JUMP_FORWARD            10 (to 5882)

680     >> 5872 LOAD_FAST                8 (h)
           5875 LOAD_CONST              23 (21)
           5878 INPLACE_SUBTRACT    
           5879 STORE_FAST               8 (h)

681     >> 5882 LOAD_FAST               13 (m)
           5885 LOAD_CONST              55 (44)
           5888 COMPARE_OP               0 (<)
           5891 POP_JUMP_IF_FALSE     5907

682        5894 LOAD_FAST                1 (a)
           5897 LOAD_CONST              30 (19)
           5900 INPLACE_SUBTRACT    
           5901 STORE_FAST               1 (a)
           5904 JUMP_FORWARD            10 (to 5917)

684     >> 5907 LOAD_FAST                1 (a)
           5910 LOAD_CONST              10 (0)
           5913 INPLACE_ADD         
           5914 STORE_FAST               1 (a)

685     >> 5917 LOAD_FAST                6 (f)
           5920 LOAD_CONST              61 (47)
           5923 COMPARE_OP               0 (<)
           5926 POP_JUMP_IF_FALSE     5942

686        5929 LOAD_FAST                9 (i)
           5932 LOAD_CONST              22 (46)
           5935 INPLACE_SUBTRACT    
           5936 STORE_FAST               9 (i)
           5939 JUMP_FORWARD            10 (to 5952)

688     >> 5942 LOAD_FAST                9 (i)
           5945 LOAD_CONST              22 (46)
           5948 INPLACE_ADD         
           5949 STORE_FAST               9 (i)

689     >> 5952 LOAD_FAST               11 (k)
           5955 LOAD_CONST              19 (3)
           5958 COMPARE_OP               0 (<)
           5961 POP_JUMP_IF_FALSE     5977

690        5964 LOAD_FAST               10 (j)
           5967 LOAD_CONST              65 (35)
           5970 INPLACE_SUBTRACT    
           5971 STORE_FAST              10 (j)
           5974 JUMP_FORWARD            10 (to 5987)

692     >> 5977 LOAD_FAST               10 (j)
           5980 LOAD_CONST              83 (88)
           5983 INPLACE_SUBTRACT    
           5984 STORE_FAST              10 (j)

693     >> 5987 LOAD_FAST                1 (a)
           5990 LOAD_CONST              10 (0)
           5993 COMPARE_OP               4 (>)
           5996 POP_JUMP_IF_FALSE     6012

694        5999 LOAD_FAST               18 (r)
           6002 LOAD_CONST              10 (0)
           6005 INPLACE_ADD         
           6006 STORE_FAST              18 (r)
           6009 JUMP_FORWARD            10 (to 6022)

696     >> 6012 LOAD_FAST               18 (r)
           6015 LOAD_CONST              55 (44)
           6018 INPLACE_SUBTRACT    
           6019 STORE_FAST              18 (r)

697     >> 6022 LOAD_FAST               18 (r)
           6025 LOAD_CONST              12 (6)
           6028 COMPARE_OP               0 (<)
           6031 POP_JUMP_IF_FALSE     6047

698        6034 LOAD_FAST               15 (o)
           6037 LOAD_CONST              23 (21)
           6040 INPLACE_SUBTRACT    
           6041 STORE_FAST              15 (o)
           6044 JUMP_FORWARD            10 (to 6057)

700     >> 6047 LOAD_FAST               15 (o)
           6050 LOAD_CONST              33 (28)
           6053 INPLACE_SUBTRACT    
           6054 STORE_FAST              15 (o)

701     >> 6057 LOAD_FAST                1 (a)
           6060 LOAD_CONST              25 (34)
           6063 COMPARE_OP               0 (<)
           6066 POP_JUMP_IF_FALSE     6082

702        6069 LOAD_FAST               14 (n)
           6072 LOAD_CONST              63 (36)
           6075 INPLACE_ADD         
           6076 STORE_FAST              14 (n)
           6079 JUMP_FORWARD            10 (to 6092)

704     >> 6082 LOAD_FAST               14 (n)
           6085 LOAD_CONST              18 (1)
           6088 INPLACE_ADD         
           6089 STORE_FAST              14 (n)

705     >> 6092 LOAD_FAST               10 (j)
           6095 LOAD_CONST              25 (34)
           6098 COMPARE_OP               0 (<)
           6101 POP_JUMP_IF_FALSE     6117

706        6104 LOAD_FAST               13 (m)
           6107 LOAD_CONST              51 (40)
           6110 INPLACE_SUBTRACT    
           6111 STORE_FAST              13 (m)
           6114 JUMP_FORWARD            10 (to 6127)

708     >> 6117 LOAD_FAST               13 (m)
           6120 LOAD_CONST              54 (61)
           6123 INPLACE_SUBTRACT    
           6124 STORE_FAST              13 (m)

709     >> 6127 LOAD_FAST               14 (n)
           6130 LOAD_CONST              46 (20)
           6133 COMPARE_OP               0 (<)
           6136 POP_JUMP_IF_FALSE     6152

710        6139 LOAD_FAST               15 (o)
           6142 LOAD_CONST              21 (7)
           6145 INPLACE_ADD         
           6146 STORE_FAST              15 (o)
           6149 JUMP_FORWARD            10 (to 6162)

712     >> 6152 LOAD_FAST               15 (o)
           6155 LOAD_CONST              21 (7)
           6158 INPLACE_SUBTRACT    
           6159 STORE_FAST              15 (o)

713     >> 6162 LOAD_FAST               14 (n)
           6165 LOAD_CONST              66 (27)
           6168 COMPARE_OP               4 (>)
           6171 POP_JUMP_IF_FALSE     6187

714        6174 LOAD_FAST                1 (a)
           6177 LOAD_CONST              10 (0)
           6180 INPLACE_ADD         
           6181 STORE_FAST               1 (a)
           6184 JUMP_FORWARD            10 (to 6197)

716     >> 6187 LOAD_FAST                1 (a)
           6190 LOAD_CONST              14 (25)
           6193 INPLACE_SUBTRACT    
           6194 STORE_FAST               1 (a)

717     >> 6197 LOAD_FAST               15 (o)
           6200 LOAD_CONST              55 (44)
           6203 COMPARE_OP               4 (>)
           6206 POP_JUMP_IF_FALSE     6222

718        6209 LOAD_FAST               13 (m)
           6212 LOAD_CONST              11 (39)
           6215 INPLACE_ADD         
           6216 STORE_FAST              13 (m)
           6219 JUMP_FORWARD            10 (to 6232)

720     >> 6222 LOAD_FAST               13 (m)
           6225 LOAD_CONST              20 (17)
           6228 INPLACE_SUBTRACT    
           6229 STORE_FAST              13 (m)

721     >> 6232 LOAD_FAST                0 (flag)
           6235 LOAD_GLOBAL              0 (chr)
           6238 LOAD_FAST                1 (a)
           6241 CALL_FUNCTION            1
           6244 INPLACE_ADD         
           6245 STORE_FAST               0 (flag)

722        6248 LOAD_FAST                0 (flag)
           6251 LOAD_GLOBAL              0 (chr)
           6254 LOAD_FAST                2 (b)
           6257 CALL_FUNCTION            1
           6260 INPLACE_ADD         
           6261 STORE_FAST               0 (flag)

723        6264 LOAD_FAST                0 (flag)
           6267 LOAD_GLOBAL              0 (chr)
           6270 LOAD_FAST                3 (c)
           6273 CALL_FUNCTION            1
           6276 INPLACE_ADD         
           6277 STORE_FAST               0 (flag)

724        6280 LOAD_FAST                0 (flag)
           6283 LOAD_GLOBAL              0 (chr)
           6286 LOAD_FAST                4 (d)
           6289 CALL_FUNCTION            1
           6292 INPLACE_ADD         
           6293 STORE_FAST               0 (flag)

725        6296 LOAD_FAST                0 (flag)
           6299 LOAD_GLOBAL              0 (chr)
           6302 LOAD_FAST                5 (e)
           6305 CALL_FUNCTION            1
           6308 INPLACE_ADD         
           6309 STORE_FAST               0 (flag)

726        6312 LOAD_FAST                0 (flag)
           6315 LOAD_GLOBAL              0 (chr)
           6318 LOAD_FAST                6 (f)
           6321 CALL_FUNCTION            1
           6324 INPLACE_ADD         
           6325 STORE_FAST               0 (flag)

727        6328 LOAD_FAST                0 (flag)
           6331 LOAD_GLOBAL              0 (chr)
           6334 LOAD_FAST                7 (g)
           6337 CALL_FUNCTION            1
           6340 INPLACE_ADD         
           6341 STORE_FAST               0 (flag)

728        6344 LOAD_FAST                0 (flag)
           6347 LOAD_GLOBAL              0 (chr)
           6350 LOAD_FAST                8 (h)
           6353 CALL_FUNCTION            1
           6356 INPLACE_ADD         
           6357 STORE_FAST               0 (flag)

729        6360 LOAD_FAST                0 (flag)
           6363 LOAD_GLOBAL              0 (chr)
           6366 LOAD_FAST                9 (i)
           6369 CALL_FUNCTION            1
           6372 INPLACE_ADD         
           6373 STORE_FAST               0 (flag)

730        6376 LOAD_FAST                0 (flag)
           6379 LOAD_GLOBAL              0 (chr)
           6382 LOAD_FAST               10 (j)
           6385 CALL_FUNCTION            1
           6388 INPLACE_ADD         
           6389 STORE_FAST               0 (flag)

731        6392 LOAD_FAST                0 (flag)
           6395 LOAD_GLOBAL              0 (chr)
           6398 LOAD_FAST               11 (k)
           6401 CALL_FUNCTION            1
           6404 INPLACE_ADD         
           6405 STORE_FAST               0 (flag)

732        6408 LOAD_FAST                0 (flag)
           6411 LOAD_GLOBAL              0 (chr)
           6414 LOAD_FAST               12 (l)
           6417 CALL_FUNCTION            1
           6420 INPLACE_ADD         
           6421 STORE_FAST               0 (flag)

733        6424 LOAD_FAST                0 (flag)
           6427 LOAD_GLOBAL              0 (chr)
           6430 LOAD_FAST               13 (m)
           6433 CALL_FUNCTION            1
           6436 INPLACE_ADD         
           6437 STORE_FAST               0 (flag)

734        6440 LOAD_FAST                0 (flag)
           6443 LOAD_GLOBAL              0 (chr)
           6446 LOAD_FAST               14 (n)
           6449 CALL_FUNCTION            1
           6452 INPLACE_ADD         
           6453 STORE_FAST               0 (flag)

735        6456 LOAD_FAST                0 (flag)
           6459 LOAD_GLOBAL              0 (chr)
           6462 LOAD_FAST               15 (o)
           6465 CALL_FUNCTION            1
           6468 INPLACE_ADD         
           6469 STORE_FAST               0 (flag)

736        6472 LOAD_FAST                0 (flag)
           6475 LOAD_GLOBAL              0 (chr)
           6478 LOAD_FAST               16 (p)
           6481 CALL_FUNCTION            1
           6484 INPLACE_ADD         
           6485 STORE_FAST               0 (flag)

737        6488 LOAD_FAST                0 (flag)
           6491 LOAD_GLOBAL              0 (chr)
           6494 LOAD_FAST               17 (q)
           6497 CALL_FUNCTION            1
           6500 INPLACE_ADD         
           6501 STORE_FAST               0 (flag)

738        6504 LOAD_FAST                0 (flag)
           6507 LOAD_GLOBAL              0 (chr)
           6510 LOAD_FAST               18 (r)
           6513 CALL_FUNCTION            1
           6516 INPLACE_ADD         
           6517 STORE_FAST               0 (flag)

739        6520 LOAD_FAST                0 (flag)
           6523 LOAD_GLOBAL              0 (chr)
           6526 LOAD_FAST               19 (s)
           6529 CALL_FUNCTION            1
           6532 INPLACE_ADD         
           6533 STORE_FAST               0 (flag)

740        6536 LOAD_FAST                0 (flag)
           6539 LOAD_GLOBAL              0 (chr)
           6542 LOAD_FAST               20 (t)
           6545 CALL_FUNCTION            1
           6548 INPLACE_ADD         
           6549 STORE_FAST               0 (flag)

741        6552 LOAD_FAST                0 (flag)
           6555 LOAD_GLOBAL              0 (chr)
           6558 LOAD_FAST               21 (u)
           6561 CALL_FUNCTION            1
           6564 INPLACE_ADD         
           6565 STORE_FAST               0 (flag)

743        6568 LOAD_FAST                0 (flag)
           6571 LOAD_CONST              84 ('}')
           6574 INPLACE_ADD         
           6575 STORE_FAST               0 (flag)

744        6578 LOAD_FAST                0 (flag)
           6581 RETURN_VALUE        
